[
    {
        "type": "qq",
        "link": "http://y.qq.com/n/yqq/song/003OUlho2HcRHC.html",
        "songid": "003OUlho2HcRHC",
        "title": "告白气球",
        "author": "周杰伦",
        "lrc": "[ti:告白气球]\n[ar:周杰伦]\n[al:周杰伦的床边故事]\n[by:]\n[offset:0]\n[00:00.00]告白气球 - 周杰伦 (Jay Chou)\n[00:07.86]词：方文山\n[00:15.72]曲：周杰伦\n[00:23.59]塞纳河畔 左岸的咖啡\n[00:26.16]我手一杯 品尝你的美\n[00:28.78]\n[00:29.33]留下唇印的嘴\n[00:31.83]\n[00:34.27]花店玫瑰 名字写错谁\n[00:36.90]告白气球 风吹到对街\n[00:39.29]\n[00:40.01]微笑在天上飞\n[00:42.10]\n[00:44.01]你说你有点难追\n[00:46.57]想让我知难而退\n[00:49.22]礼物不需挑最贵\n[00:51.89]只要香榭的落叶\n[00:54.56]喔 营造浪漫的约会\n[00:57.26]不害怕搞砸一切\n[00:59.93]拥有你就拥有全世界\n[01:04.10]\n[01:05.01]亲爱的 爱上你\n[01:08.17]从那天起\n[01:10.61]\n[01:11.33]甜蜜的很轻易\n[01:14.43]\n[01:15.69]亲爱的 别任性\n[01:18.85]你的眼睛\n[01:21.24]\n[01:21.94]在说我愿意\n[01:25.23]\n[01:48.90]塞纳河畔 左岸的咖啡\n[01:51.46]我手一杯 品尝你的美\n[01:54.43]留下唇印的嘴\n[01:56.63]\n[01:59.56]花店玫瑰 名字写错谁\n[02:02.14]告白气球 风吹到对街\n[02:04.37]\n[02:05.23]微笑在天上飞\n[02:07.49]\n[02:09.29]你说你有点难追\n[02:11.90]想让我知难而退\n[02:14.60]礼物不需挑最贵\n[02:17.26]只要香榭的落叶\n[02:19.93]喔 营造浪漫的约会\n[02:22.65]不害怕搞砸一切\n[02:25.27]拥有你就拥有 全世界\n[02:29.23]\n[02:30.31]亲爱的 爱上你\n[02:33.58]从那天起\n[02:36.03]\n[02:36.60]甜蜜的很轻易\n[02:39.65]\n[02:40.94]亲爱的 别任性\n[02:44.20]你的眼睛\n[02:46.70]\n[02:47.26]在说我愿意\n[02:50.81]\n[02:51.76]亲爱的 爱上你\n[02:54.52]\n[02:55.05]恋爱日记\n[02:57.30]\n[02:57.93]飘香水的回忆\n[03:00.72]\n[03:02.33]一整瓶 的梦境\n[03:05.42]全都有你\n[03:07.91]\n[03:08.64]搅拌在一起\n[03:11.39]\n[03:13.02]亲爱的别任性\n[03:16.23]你的眼睛\n[03:19.99]\n[03:21.31]在说我愿意",
        "url": "http://dl.stream.qqmusic.qq.com/M500003OUlho2HcRHC.mp3?vkey=020AA914D82987A535947BF07B44F9984E8AEFB10ED36B5EEF847056E72E339C5D6393C7355EB98B445D9534D85AF3FCA05B81662834DD5C&guid=5150825362&fromtag=1",
        "pic": "http://y.gtimg.cn/music/photo_new/T002R300x300M000003RMaRI1iFoYd.jpg"
    },
    {
        "type": "qq",
        "link": "http://y.qq.com/n/yqq/song/002qU5aY3Qu24y.html",
        "songid": "002qU5aY3Qu24y",
        "title": "青花瓷",
        "author": "周杰伦",
        "lrc": "[ti:青花瓷]\n[ar:周杰伦]\n[al:我很忙]\n[by:]\n[offset:0]\n[00:00.00]青花瓷 - 周杰伦 (Jay Chou)\n[00:05.49]词：方文山\n[00:10.99]曲：周杰伦\n[00:16.48]编曲：钟兴民\n[00:21.98]素胚勾勒出青花笔锋浓转淡\n[00:26.29]瓶身描绘的牡丹一如你初妆\n[00:30.72]冉冉檀香透过窗心事我了然\n[00:35.20]宣纸上走笔至此搁一半\n[00:39.69]釉色渲染仕女图韵味被私藏\n[00:44.00]而你嫣然的一笑如含苞待放\n[00:48.48]你的美一缕飘散\n[00:50.95]去到我去不了的地方\n[00:55.75]\n[00:57.50]天青色等烟雨 而我在等你\n[01:01.86]炊烟袅袅升起 隔江千万里\n[01:05.79]\n[01:06.36]在瓶底书汉隶仿前朝的飘逸\n[01:09.99]\n[01:10.75]就当我为遇见你伏笔\n[01:15.19]天青色等烟雨 而我在等你\n[01:19.58]月色被打捞起 晕开了结局\n[01:24.05]如传世的青花瓷自顾自美丽\n[01:28.01]你眼带笑意\n[01:31.22]\n[01:50.82]色白花青的锦鲤跃然于碗底\n[01:55.20]临摹宋体落款时却惦记着你\n[01:59.65]你隐藏在窑烧里千年的秘密\n[02:04.09]极细腻犹如绣花针落地\n[02:08.61]帘外芭蕉惹骤雨门环惹铜绿\n[02:12.94]而我路过那江南小镇惹了你\n[02:17.31]在泼墨山水画里\n[02:19.80]你从墨色深处被隐去\n[02:24.17]\n[02:26.45]天青色等烟雨 而我在等你\n[02:30.76]炊烟袅袅升起 隔江千万里\n[02:35.15]在瓶底书汉隶仿前朝的飘逸\n[02:38.98]\n[02:39.71]就当我为遇见你伏笔\n[02:44.10]天青色等烟雨 而我在等你\n[02:48.50]月色被打捞起 晕开了结局\n[02:52.96]如传世的青花瓷自顾自美丽\n[02:56.85]你眼带笑意\n[03:00.36]\n[03:01.95]天青色等烟雨 而我在等你\n[03:06.27]炊烟袅袅升起 隔江千万里\n[03:10.79]在瓶底书汉隶仿前朝的飘逸\n[03:15.23]就当我为遇见你伏笔\n[03:19.65]天青色等烟雨 而我在等你\n[03:24.06]月色被打捞起 晕开了结局\n[03:28.50]如传世的青花瓷自顾自美丽\n[03:32.38]你眼带笑意",
        "url": "http://dl.stream.qqmusic.qq.com/M500002qU5aY3Qu24y.mp3?vkey=020AA914D82987A535947BF07B44F9984E8AEFB10ED36B5EEF847056E72E339C5D6393C7355EB98B445D9534D85AF3FCA05B81662834DD5C&guid=5150825362&fromtag=1",
        "pic": "http://y.gtimg.cn/music/photo_new/T002R300x300M000002eFUFm2XYZ7z.jpg"
    },
    {
        "type": "qq",
        "link": "http://y.qq.com/n/yqq/song/002l8JN71d2Dxy.html",
        "songid": "002l8JN71d2Dxy",
        "title": "龙卷风",
        "author": "周杰伦",
        "lrc": "[ti:龙卷风]\n[ar:周杰伦]\n[al:Jay]\n[by:]\n[offset:0]\n[00:00.00]龙卷风 - 周杰伦 (Jay Chou)\n[00:05.49]词：徐若瑄\n[00:10.99]曲：周杰伦\n[00:16.49]编曲：周杰伦\n[00:21.98]制作人：周杰伦\n[00:27.48]爱像一阵风 吹完它就走\n[00:34.00]这样的节奏 谁都无可奈何\n[00:40.76]没有你以后 我灵魂失控\n[00:47.36]黑云在降落 我被它拖着走\n[00:53.67]静静悄悄默默离开\n[00:57.01]陷入了危险边缘Baby\n[01:01.18]我的世界已狂风暴雨 wu\n[01:07.43]爱情来的太快 就像龙卷风\n[01:10.79]离不开暴风圈 来不及逃\n[01:13.77]我不能再想 我不能再想\n[01:16.97]我不 我不 我不能\n[01:19.42]\n[01:20.95]爱情走的太快 就像龙卷风\n[01:24.06]不能承受 我已无处可躲\n[01:27.08]我不要再想 我不要再想\n[01:30.40]我不 我不 我不要再想你\n[01:34.38]不知不觉 你已经离开我\n[01:37.51]不知不觉 我跟了这节奏\n[01:40.82]后知后觉 又过了一个秋\n[01:44.03]后知后觉 我该好好生活\n[01:47.46]静静悄悄默默离开\n[01:50.35]陷入了危险边缘Baby\n[01:54.50]我的世界已狂风暴雨 wu\n[02:00.77]爱情来的太快 就像龙卷风\n[02:04.15]离不开暴风圈 来不及逃\n[02:07.06]我不能再想 我不能再想\n[02:10.38]我不 我不 我不能\n[02:12.66]\n[02:14.18]爱情走的太快 就像龙卷风\n[02:17.36]不能承受 我已无处可躲\n[02:20.39]我不要再想 我不要再想\n[02:23.69]我不 我不 我不要再想你\n[02:29.88]\n[02:54.30]爱情来的太快 就像龙卷风\n[02:57.54]离不开暴风圈 来不及逃\n[03:00.43]我不能再想 我不能再想\n[03:03.76]我不 我不 我不能\n[03:06.25]\n[03:07.59]爱情走的太快 就像龙卷风\n[03:10.85]不能承受 我已无处可躲\n[03:13.78]我不要再想 我不要再想\n[03:17.07]我不 我不 我不要再想你\n[03:21.05]不知不觉 你已经离开我\n[03:24.15]不知不觉 我跟了这节奏\n[03:27.45]后知后觉 又过了一个秋\n[03:30.75]后知后觉 我该好好生活\n[03:34.17]不知不觉 你已经离开我\n[03:37.41]不知不觉 我跟了这节奏\n[03:40.71]后知后觉 又过了一个秋\n[03:44.17]后知后觉 我该好好生活\n[03:47.40]不知不觉 你已经离开我\n[03:50.90]不知不觉 我跟了这节奏\n[03:54.35]后知后觉 后知后觉",
        "url": "http://dl.stream.qqmusic.qq.com/M500002l8JN71d2Dxy.mp3?vkey=020AA914D82987A535947BF07B44F9984E8AEFB10ED36B5EEF847056E72E339C5D6393C7355EB98B445D9534D85AF3FCA05B81662834DD5C&guid=5150825362&fromtag=1",
        "pic": "http://y.gtimg.cn/music/photo_new/T002R300x300M000000f01724fd7TH.jpg"
    },
    {
        "type": "qq",
        "link": "http://y.qq.com/n/yqq/song/003aAYrm3GE0Ac.html",
        "songid": "003aAYrm3GE0Ac",
        "title": "稻香",
        "author": "周杰伦",
        "lrc": "[ti:稻香]\n[ar:周杰伦]\n[al:魔杰座]\n[by:]\n[offset:0]\n[00:00.00]稻香 - 周杰伦 (Jay Chou)\n[00:10.22]词：周杰伦\n[00:20.44]曲：周杰伦\n[00:30.66]对这个世界如果你有太多的抱怨\n[00:34.11]跌倒了就不敢继续往前走\n[00:37.07]为什么人要这么的脆弱堕落\n[00:41.50]请你打开电视看看\n[00:43.05]多少人为生命在努力勇敢的走下去\n[00:47.03]我们是不是该知足\n[00:49.46]珍惜一切就算没有拥有\n[00:52.92]\n[00:54.04]还记得你说家是唯一的城堡\n[00:57.63]随着稻香河流继续奔跑\n[01:00.57]微微笑 小时候的梦我知道\n[01:04.34]\n[01:05.73]不要哭让萤火虫带着你逃跑\n[01:09.24]乡间的歌谣永远的依靠\n[01:12.17]回家吧 回到最初的美好\n[01:16.87]\n[01:41.00]不要这么容易就想放弃\n[01:43.14]就像我说的\n[01:44.54]追不到的梦想换个梦不就得了\n[01:47.58]为自己的人生鲜艳上色\n[01:49.88]先把爱涂上喜欢的颜色\n[01:52.56]笑一个吧\n[01:53.61]功成名就不是目的\n[01:55.61]让自己快乐快乐这才叫做意义\n[01:58.58]童年的纸飞机\n[02:00.10]现在终于飞回我手里\n[02:02.88]\n[02:04.29]所谓的那快乐\n[02:05.72]赤脚在田里追蜻蜓追到累了\n[02:08.70]偷摘水果被蜜蜂给叮到怕了\n[02:11.74]谁在偷笑呢\n[02:13.24]我靠着稻草人\n[02:14.49]吹着风 唱着歌 睡着了\n[02:17.55]午后吉他在虫鸣中更清脆\n[02:19.66]\n[02:20.45]阳光洒在路上就不怕心碎\n[02:23.17]珍惜一切 就算没有拥有\n[02:26.28]\n[02:27.76]还记得你说家是唯一的城堡\n[02:31.33]随着稻香河流继续奔跑\n[02:34.19]微微笑 小时候的梦我知道\n[02:38.03]\n[02:39.25]不要哭让萤火虫带着你逃跑\n[02:42.94]乡间的歌谣永远的依靠\n[02:46.01]回家吧 回到最初的美好\n[02:51.09]还记得你说家是唯一的城堡\n[02:54.73]随着稻香河流继续奔跑\n[02:57.67]微微笑 小时候的梦我知道\n[03:01.73]\n[03:02.78]不要哭让萤火虫带着你逃跑\n[03:06.44]乡间的歌谣永远的依靠\n[03:09.40]回家吧 回到最初的美好",
        "url": "http://dl.stream.qqmusic.qq.com/M500003aAYrm3GE0Ac.mp3?vkey=020AA914D82987A535947BF07B44F9984E8AEFB10ED36B5EEF847056E72E339C5D6393C7355EB98B445D9534D85AF3FCA05B81662834DD5C&guid=5150825362&fromtag=1",
        "pic": "http://y.gtimg.cn/music/photo_new/T002R300x300M000002Neh8l0uciQZ.jpg"
    },
    {
        "type": "qq",
        "link": "http://y.qq.com/n/yqq/song/001J5QJL1pRQYB.html",
        "songid": "001J5QJL1pRQYB",
        "title": "等你下课(with 杨瑞代)",
        "author": "周杰伦",
        "lrc": "[ti:等你下课(with 杨瑞代)]\n[ar:周杰伦]\n[al:]\n[by:]\n[offset:0]\n[00:01.74]等你下课(with 杨瑞代) - 周杰伦 (Jay Chou)\n[00:08.09]词：周杰伦\n[00:10.18]曲：周杰伦\n[00:12.61]\n[00:15.16]Jay：你住的 巷子里\n[00:18.77]我租了一间公寓\n[00:21.93]\n[00:22.48]为了想与你不期而遇\n[00:27.25]\n[00:28.55]高中三年 我为什么\n[00:31.60]为什么不好好读书\n[00:34.55]\n[00:35.69]没考上跟你一样的大学\n[00:39.89]\n[00:40.64]我找了份工作\n[00:42.89]\n[00:43.73]离你宿舍很近\n[00:46.23]\n[00:46.98]当我开始学会做蛋饼\n[00:50.41]才发现你 不吃早餐\n[00:55.24]喔 你又擦肩而过\n[00:59.33]\n[01:00.01]你耳机听什么\n[01:02.52]\n[01:03.18]能不能告诉我\n[01:05.64]\n[01:06.74]合：躺在你学校的操场看星空\n[01:13.50]\n[01:14.32]教室里的灯还亮着你没走\n[01:19.76]\n[01:20.78]记得 我写给你的情书\n[01:26.32]\n[01:27.28]都什么年代了\n[01:29.68]\n[01:30.54]到现在我还在写着\n[01:34.17]总有一天总有一年会发现\n[01:39.54]\n[01:40.30]有人默默的陪在你的身边\n[01:46.10]\n[01:46.97]也许 我不该在你的世界\n[01:52.47]\n[01:53.33]当你收到情书\n[01:55.70]\n[01:56.78]也代表我已经走远\n[02:01.67]\n[02:24.25]Gary：学校旁 的广场\n[02:27.98]\n[02:28.54]我在这等钟声响\n[02:31.36]\n[02:32.39]等你下课一起走好吗\n[02:37.34]Jay：弹着琴 唱你爱的歌\n[02:41.52]暗恋一点都不痛苦\n[02:43.88]Gary：一点都不痛苦\n[02:45.43]Jay：痛苦的是你\n[02:46.83]合：根本没看我\n[02:49.75]Jay：我唱这么走心\n[02:52.23]Gary：这么走心\n[02:53.40]Jay：却走不进你心里\n[02:55.49]Gary：进你心里\n[02:56.96]Jay：在人来人往\n[02:58.50]合：找寻着你 守护着你\n[03:01.74]不求结局\n[03:04.63]合：喔\n[03:06.13]Gary：你又擦肩\n[03:07.57]合：而过\n[03:08.97]\n[03:09.62]Jay：我唱告白气球\n[03:11.86]\n[03:12.94]终于你回了头\n[03:15.69]\n[03:16.94]合：躺在你学校的操场看星空\n[03:23.27]\n[03:24.23]教室里的灯还亮着你没走\n[03:29.54]\n[03:30.58]记得 我写给你的情书\n[03:35.76]\n[03:37.04]都什么年代了\n[03:39.09]\n[03:40.19]到现在我还在写着\n[03:43.89]总有一天总有一年会发现\n[03:49.31]\n[03:50.07]有人默默的陪在你的身边\n[03:55.87]\n[03:56.68]也许 我不该在你的世界\n[04:02.12]\n[04:02.98]当你收到情书\n[04:05.29]\n[04:06.59]也代表我已经走远",
        "url": "http://dl.stream.qqmusic.qq.com/M500001J5QJL1pRQYB.mp3?vkey=020AA914D82987A535947BF07B44F9984E8AEFB10ED36B5EEF847056E72E339C5D6393C7355EB98B445D9534D85AF3FCA05B81662834DD5C&guid=5150825362&fromtag=1",
        "pic": "http://y.gtimg.cn/music/photo_new/T002R300x300M000003bSL0v4bpKAx.jpg"
    },
    {
        "type": "qq",
        "link": "http://y.qq.com/n/yqq/song/0039MnYb0qxYhV.html",
        "songid": "0039MnYb0qxYhV",
        "title": "晴天",
        "author": "周杰伦",
        "lrc": "[ti:晴天]\n[ar:周杰伦]\n[al:叶惠美]\n[by:]\n[offset:0]\n[00:00.00]晴天 - 周杰伦 (Jay Chou)\n[00:07.34]词：周杰伦\n[00:14.69]曲：周杰伦\n[00:22.04]编曲：周杰伦\n[00:29.39]故事的小黄花\n[00:32.64]从出生那年就飘着\n[00:36.19]童年的荡秋千\n[00:39.93]随记忆一直晃到现在\n[00:42.99]Re So So Si Do Si La \n[00:46.11]So La Si Si Si Si La Si La So \n[00:49.79]吹着前奏望着天空\n[00:53.35]我想起花瓣试着掉落\n[00:56.78]为你翘课的那一天\n[00:59.03]花落的那一天\n[01:00.65]教室的那一间\n[01:02.21]我怎么看不见\n[01:04.02]消失的下雨天\n[01:05.71]我好想再淋一遍\n[01:09.08]\n[01:09.95]没想到失去的勇气我还留着\n[01:15.01]\n[01:16.13]好想再问一遍\n[01:17.87]你会等待还是离开\n[01:23.18]\n[01:24.74]刮风这天我试过握着你手\n[01:30.42]但偏偏雨渐渐大到我看你不见\n[01:37.66]\n[01:38.84]还要多久我才能在你身边\n[01:44.65]\n[01:45.40]等到放晴的那天也许我会比较好一点\n[01:52.76]从前从前有个人爱你很久\n[01:58.50]但偏偏风渐渐把距离吹得好远\n[02:05.86]\n[02:06.74]好不容易又能再多爱一天\n[02:13.35]但故事的最后你好像还是说了拜拜\n[02:21.46]\n[02:35.00]为你翘课的那一天\n[02:36.75]花落的那一天\n[02:38.63]教室的那一间\n[02:40.31]我怎么看不见\n[02:42.05]消失的下雨天\n[02:43.74]我好想再淋一遍\n[02:46.99]\n[02:47.98]没想到失去的勇气我还留着\n[02:53.60]\n[02:54.53]好想再问一遍\n[02:55.97]你会等待还是离开\n[03:01.77]\n[03:02.77]刮风这天我试过握着你手\n[03:08.45]但偏偏雨渐渐大到我看你不见\n[03:15.94]\n[03:16.87]还要多久我才能在你身边\n[03:23.49]等到放晴的那天也许我会比较好一点\n[03:30.91]从前从前有个人爱你很久\n[03:37.03]偏偏风渐渐把距离吹得好远\n[03:43.89]\n[03:44.77]好不容易又能再多爱一天\n[03:50.38]\n[03:51.07]但故事的最后你好像还是说了拜拜\n[03:59.62]刮风这天我试过握着你手\n[04:02.05]但偏偏雨渐渐大到我看你不见\n[04:05.44]还要多久我才能够在你身边\n[04:08.99]等到放晴那天也许我会比较好一点\n[04:12.86]从前从前有个人爱你很久\n[04:15.86]但偏偏雨渐渐把距离吹得好远\n[04:19.29]好不容易又能再多爱一天\n[04:22.79]但故事的最后你好像还是说了拜",
        "url": "http://dl.stream.qqmusic.qq.com/M5000039MnYb0qxYhV.mp3?vkey=020AA914D82987A535947BF07B44F9984E8AEFB10ED36B5EEF847056E72E339C5D6393C7355EB98B445D9534D85AF3FCA05B81662834DD5C&guid=5150825362&fromtag=1",
        "pic": "http://y.gtimg.cn/music/photo_new/T002R300x300M000000MkMni19ClKG.jpg"
    },
    {
        "type": "qq",
        "link": "http://y.qq.com/n/yqq/song/0042QMDR1VzSsx.html",
        "songid": "0042QMDR1VzSsx",
        "title": "说好的幸福呢",
        "author": "周杰伦",
        "lrc": "[ti:说好的幸福呢]\n[ar:周杰伦]\n[al:闪亮2008 Hit Fm 年度百首单曲]\n[by:]\n[offset:0]\n[00:00.00]说好的幸福呢 - 周杰伦 (Jay Chou)\n[00:05.70]词：方文山\n[00:11.40]曲：周杰伦\n[00:17.10]编曲：钟兴民\n[00:22.80]你的回话凌乱着\n[00:26.42]\n[00:27.09]在这个时刻\n[00:30.16]\n[00:30.76]我想起喷泉旁的白鸽\n[00:35.30]甜蜜散落了\n[00:38.10]\n[00:38.83]情绪莫名的拉扯\n[00:42.41]\n[00:43.44]我还爱你呢\n[00:46.93]而你断断续续唱着歌\n[00:51.07]\n[00:51.58]假装没事了\n[00:54.69]时间过了走了\n[00:57.20]爱情面临选择\n[00:59.80]你冷了倦了我哭了\n[01:03.18]离开时的不快乐\n[01:05.20]你用卡片手写着\n[01:07.19]有些爱只给到这\n[01:08.98]真的痛了\n[01:12.43]\n[01:13.41]怎么了你累了说好的\n[01:16.38]幸福呢\n[01:17.45]我懂了不说了\n[01:19.44]爱淡了梦远了\n[01:21.48]开心与不开心一一\n[01:23.56]细数着你再不舍\n[01:25.57]那些爱过的感觉都太深刻\n[01:28.43]我都还记得\n[01:30.42]你不等了说好的\n[01:32.69]幸福呢\n[01:33.74]我错了泪干了\n[01:35.78]放手了后悔了\n[01:37.86]只是回忆的音乐盒\n[01:39.91]还旋转着要怎么停呢\n[01:44.75]\n[01:56.72]你的回话凌乱着\n[01:59.92]\n[02:01.06]在这个时刻\n[02:04.17]\n[02:04.77]我想起喷泉旁的白鸽\n[02:08.70]\n[02:09.23]甜蜜散落了\n[02:12.18]\n[02:12.77]情绪莫名的拉扯\n[02:16.37]\n[02:17.42]我还爱你呢\n[02:21.00]而你断断续续唱着歌\n[02:25.57]假装没事了\n[02:28.59]时间过了走了\n[02:31.07]爱情面临选择\n[02:33.19]\n[02:33.72]你冷了倦了我哭了\n[02:37.09]离开时的不快乐\n[02:39.12]你用卡片手写着\n[02:41.15]有些爱只给到这真的痛了\n[02:46.66]\n[02:47.37]怎么了你累了\n[02:49.34]说好的幸福呢\n[02:51.39]我懂了不说了\n[02:53.41]爱淡了梦远了\n[02:55.46]开心与不开心一一\n[02:57.52]细数着你再不舍\n[02:59.55]那些爱过的感觉都太深刻\n[03:02.30]我都还记得\n[03:04.39]你不等了说好的幸福呢\n[03:07.71]我错了泪干了\n[03:09.73]放手了后悔了\n[03:11.79]只是回忆的音乐盒\n[03:13.84]还旋转着\n[03:15.45]要怎么停呢\n[03:19.00]\n[03:19.64]怎么了你累了\n[03:23.39]\n[03:24.21]说好的幸福呢\n[03:27.95]我懂了不说了爱淡了\n[03:34.16]梦远了我都还记得\n[03:37.08]你不等了说好的幸福呢\n[03:40.38]我错了泪干了\n[03:42.41]放手了后悔了\n[03:44.45]只是回忆的音乐盒\n[03:46.54]还旋转着\n[03:48.09]要怎么停呢",
        "url": "http://dl.stream.qqmusic.qq.com/M5000042QMDR1VzSsx.mp3?vkey=020AA914D82987A535947BF07B44F9984E8AEFB10ED36B5EEF847056E72E339C5D6393C7355EB98B445D9534D85AF3FCA05B81662834DD5C&guid=5150825362&fromtag=1",
        "pic": "http://y.gtimg.cn/music/photo_new/T002R300x300M000002Neh8l0uciQZ.jpg"
    },
    {
        "type": "qq",
        "link": "http://y.qq.com/n/yqq/song/001Js78a40BZU6.html",
        "songid": "001Js78a40BZU6",
        "title": "算什么男人",
        "author": "周杰伦",
        "lrc": "[ti:算什么男人]\n[ar:1]\n[al:]\n[by:]\n[offset:0]\n[00:00.00]算什么男人 - 周杰伦 (Jay Chou)\n[00:07.59]词：周杰伦\n[00:15.19]曲：周杰伦\n[00:22.79]编曲：黄雨勋\n[00:30.38]制作人：周杰伦\n[00:37.98]亲吻你的手\n[00:40.02]还靠着你的头\n[00:42.30]让你躺胸口\n[00:44.15]那个人已不是我\n[00:47.04]这些平常的举动现在叫做难过\n[00:52.04]喔 难过\n[00:54.28]\n[00:55.89]日子开始过\n[00:57.96]我没你照样过\n[01:00.35]不会很难受\n[01:02.12]我会默默的接受\n[01:04.83]反正在一起时你我都有开心过\n[01:09.94]就足够\n[01:12.23]\n[01:13.81]我的温暖你的冷漠让爱起雾了\n[01:18.44]如果爱心画在起雾的窗是模糊\n[01:25.10]还是更清楚\n[01:28.95]\n[01:29.94]你算什么男人\n[01:32.37]算什么男人\n[01:34.64]眼睁睁看她走却不闻不问\n[01:38.78]是有多天真  就别再硬撑\n[01:43.34]期待你挽回你却拱手让人\n[01:47.85]你算什么男人\n[01:50.25]算什么男人\n[01:52.49]还爱着她却不敢叫她再等\n[01:56.76]没差 你再继续认份\n[01:59.90]她会遇到更好的男人\n[02:05.44]\n[02:21.12]亲吻你的手\n[02:23.11]还靠着你的头\n[02:25.26]让你躺胸口\n[02:27.22]那个人已不是我\n[02:30.22]这些平常的举动现在叫做难过\n[02:35.08]喔 难过\n[02:37.56]\n[02:39.00]日子开始过\n[02:41.13]我没你照样过\n[02:43.43]不会很难受\n[02:45.17]我会默默的接受\n[02:47.95]反正在一起时你我都有开心过\n[02:53.05]就足够\n[02:55.15]\n[02:57.01]我的温暖你的冷漠让爱起雾了\n[03:01.69]如果爱心画在起雾的窗是模糊\n[03:08.57]还是更清楚\n[03:13.04]你算什么男人\n[03:15.44]算什么男人\n[03:17.79]眼睁睁看她走却不闻不问\n[03:21.99]是有多天真  就别再硬撑\n[03:26.36]期待你挽回你却拱手让人\n[03:30.83]你算什么男人\n[03:33.43]算什么男人\n[03:35.73]还爱着她却不敢叫她再等\n[03:39.89]没差 你再继续认份\n[03:42.95]她会遇到更好的男人\n[03:48.12]\n[03:49.10]你算什么男人\n[03:51.28]算什么男人\n[03:53.66]眼睁睁看她走却不闻不问\n[03:57.84]是有多天真  就别再硬撑\n[04:02.35]期待你挽回却拱手让人\n[04:06.82]你算什么男人\n[04:09.26]算什么男人\n[04:11.68]还爱着她却不敢叫她再等\n[04:15.76]没差 你再继续认份\n[04:18.94]她会遇到更好的男人",
        "url": "http://dl.stream.qqmusic.qq.com/M500001Js78a40BZU6.mp3?vkey=020AA914D82987A535947BF07B44F9984E8AEFB10ED36B5EEF847056E72E339C5D6393C7355EB98B445D9534D85AF3FCA05B81662834DD5C&guid=5150825362&fromtag=1",
        "pic": "http://y.gtimg.cn/music/photo_new/T002R300x300M000001uqejs3d6EID.jpg"
    },
    {
        "type": "qq",
        "link": "http://y.qq.com/n/yqq/song/000oW8J53xPhZA.html",
        "songid": "000oW8J53xPhZA",
        "title": "明明就",
        "author": "周杰伦",
        "lrc": "[ti:明明就]\n[ar:周杰伦]\n[al:十二新作]\n[by:]\n[offset:0]\n[00:00.00]明明就 (夢で逢うだろう) - 周杰伦 (Jay Chou)\n[00:04.81]词：方文山\n[00:09.63]曲：周杰伦\n[00:14.44]编曲：黄雨勋\n[00:19.26]糖果罐里好多颜色\n[00:23.56]微笑却不甜了\n[00:27.74]你的某些快乐\n[00:30.92]在没有我的时刻\n[00:34.67]\n[00:36.29]中古世纪的城市里\n[00:40.53]我想就走到这\n[00:44.77]海鸥不再眷恋大海\n[00:49.02]可以飞更远\n[00:51.58]远方传来风笛\n[00:55.94]我只在意有你的消息\n[01:00.12]城堡为爱守着秘密\n[01:04.37]而我为你守着回忆\n[01:08.05]明明就 不习惯 牵手\n[01:12.42]为何却主动把手勾\n[01:16.54]你的心事太多\n[01:20.28]我不会戳破\n[01:23.71]\n[01:25.09]明明就 他比较 温柔\n[01:29.39]也许他能给你更多\n[01:34.63]不用抉择 我会自动变朋友\n[01:40.56]\n[01:56.97]糖果罐里好多颜色\n[02:01.21]微笑却不甜了\n[02:05.52]你的某些快乐\n[02:08.64]在没有我的时刻\n[02:12.26]\n[02:13.95]中古世纪的城市里\n[02:18.19]我想就走到这\n[02:22.37]海鸥不再眷恋大海\n[02:26.61]可以飞更远\n[02:29.36]远方传来风笛\n[02:33.47]我只在意有你的消息\n[02:37.78]城堡为爱守着秘密\n[02:42.09]而我为你守着回忆\n[02:45.77]明明就 不习惯 牵手\n[02:50.14]为何却主动把手勾\n[02:54.19]你的心事太多 我不会戳破\n[03:02.75]明明就 他比较 温柔\n[03:07.05]也许他能给你更多\n[03:12.29]不用抉择 我会自动变朋友\n[03:18.41]\n[03:35.56]明明就 明明就\n[03:37.37]明明就 他比较 温柔\n[03:41.37]也许他能给你更多\n[03:46.38]不用抉择 我会自动变朋友",
        "url": "http://dl.stream.qqmusic.qq.com/M500000oW8J53xPhZA.mp3?vkey=020AA914D82987A535947BF07B44F9984E8AEFB10ED36B5EEF847056E72E339C5D6393C7355EB98B445D9534D85AF3FCA05B81662834DD5C&guid=5150825362&fromtag=1",
        "pic": "http://y.gtimg.cn/music/photo_new/T002R300x300M000003Ow85E3pnoqi.jpg"
    },
    {
        "type": "qq",
        "link": "http://y.qq.com/n/yqq/song/000amRvH3wxv56.html",
        "songid": "000amRvH3wxv56",
        "title": "安静",
        "author": "周杰伦",
        "lrc": "[ti:安静]\n[ar:周杰伦]\n[al:范特西]\n[by:]\n[offset:0]\n[00:00.00]安静 - 周杰伦 (Jay Chou)\n[00:06.99]词：周杰伦\n[00:13.99]曲：周杰伦\n[00:20.98]编曲：钟兴民\n[00:27.98]只剩下钢琴陪我谈了一天\n[00:32.39]\n[00:33.34]睡着的大提琴 安静的旧旧的\n[00:38.98]\n[00:41.33]我想你已表现的非常明白\n[00:45.51]\n[00:46.48]我懂我也知道 你没有舍不得\n[00:52.42]\n[00:54.46]你说你也会难过我不相信\n[00:59.13]\n[01:00.93]牵着你陪着我 也只是曾经\n[01:06.09]\n[01:06.99]希望他是真的比我还要爱你\n[01:12.90]\n[01:13.66]我才会逼自己离开\n[01:17.91]\n[01:21.47]你要我说多难堪 我根本不想分开\n[01:28.14]为什么还要我用微笑来带过\n[01:33.39]\n[01:34.75]我没有这种天分 包容你也接受他\n[01:41.44]不用担心的太多 我会一直好好过\n[01:48.06]你已经远远离开 我也会慢慢走开\n[01:54.18]\n[01:54.69]为什么我连分开都迁就着你\n[02:00.47]\n[02:01.42]我真的没有天分 安静的没这么快\n[02:08.09]我会学着放弃你 是因为我太爱你\n[02:14.77]\n[02:28.14]只剩下钢琴陪我谈了一天\n[02:32.64]\n[02:33.30]睡着的大提琴 安静的旧旧的\n[02:39.22]\n[02:41.42]我想你已表现的非常明白\n[02:45.90]\n[02:46.81]我懂我也知道 你没有舍不得\n[02:52.98]\n[02:54.76]你说你也会难过我不相信\n[02:59.94]\n[03:01.40]牵着你陪着我 也只是曾经\n[03:06.03]\n[03:07.32]希望他是真的比我还要爱你\n[03:12.85]\n[03:14.01]我才会逼自己离开\n[03:18.22]\n[03:21.97]你要我说多难堪 我根本不想分开\n[03:28.62]为什么还要我用微笑来带过\n[03:33.90]\n[03:35.18]我没有这种天分 包容你也接受他\n[03:41.33]\n[03:41.89]不用担心的太多 我会一直好好过\n[03:47.92]\n[03:48.54]你已经远远离开 我也会慢慢走开\n[03:55.23]为什么我连分开都迁就着你\n[04:00.77]\n[04:01.87]我真的没有天分 安静的没这么快\n[04:08.05]\n[04:08.62]我会学着放弃你 是因为我太爱你\n[04:15.15]\n[04:19.50]你要我说多难堪 我根本不想分开\n[04:26.08]为什么还要我用微笑来带过\n[04:31.57]\n[04:32.73]我没有这种天分 包容你也接受他\n[04:38.85]\n[04:39.44]不用担心的太多 我会一直好好过\n[04:45.65]\n[04:46.40]你已经远远离开 我也会慢慢走开\n[04:52.53]\n[04:53.07]为什么我连分开都迁就着你\n[04:58.40]\n[04:59.73]我真的没有天分 安静的没这么快\n[05:05.80]\n[05:06.42]我会学着放弃你 是因为我太爱你",
        "url": "http://dl.stream.qqmusic.qq.com/M500000amRvH3wxv56.mp3?vkey=020AA914D82987A535947BF07B44F9984E8AEFB10ED36B5EEF847056E72E339C5D6393C7355EB98B445D9534D85AF3FCA05B81662834DD5C&guid=5150825362&fromtag=1",
        "pic": "http://y.gtimg.cn/music/photo_new/T002R300x300M000000I5jJB3blWeN.jpg"
    },
    {
        "type": "qq",
        "link": "http://y.qq.com/n/yqq/song/004Z8Ihr0JIu5s.html",
        "songid": "004Z8Ihr0JIu5s",
        "title": "七里香",
        "author": "周杰伦",
        "lrc": "[ti:七里香]\n[ar:周杰伦]\n[al:七里香]\n[by:]\n[offset:0]\n[00:00.00]七里香 - 周杰伦 (Jay Chou)\n[00:06.96]词：方文山\n[00:13.93]曲：周杰伦\n[00:20.90]编曲：钟兴民\n[00:27.87]窗外的麻雀在电线杆上多嘴\n[00:34.52]你说这一句很有夏天的感觉\n[00:41.23]手中的铅笔在纸上来来回回\n[00:47.58]我用几行字形容你是我的谁\n[00:53.33]\n[00:54.31]秋刀鱼的滋味猫跟你都想了解\n[01:01.65]初恋的香味就这样被我们寻回\n[01:07.74]那温暖的阳光像刚摘的鲜艳草莓\n[01:14.21]你说你舍不得吃掉这一种感觉\n[01:20.91]雨下整夜我的爱溢出就像雨水\n[01:27.67]院子落叶跟我的思念厚厚一叠\n[01:34.41]几句是非也无法将我的热情冷却\n[01:41.41]\n[01:41.95]你出现在我诗的每一页\n[01:48.11]雨下整夜我的爱溢出就像雨水\n[01:54.64]窗台蝴蝶像诗里纷飞的美丽章节\n[02:01.42]我接着写\n[02:03.91]把永远爱你写进诗的结尾\n[02:08.98]你是我唯一想要的了解\n[02:14.80]\n[02:42.26]雨下整夜我的爱溢出就像雨水\n[02:48.68]院子落叶跟我的思念厚厚一叠\n[02:55.43]几句是非也无法将我的热情冷却\n[03:03.03]你出现在我诗的每一页\n[03:08.79]\n[03:09.46]那饱满的稻穗幸福了这个季节\n[03:16.77]而你的脸颊像田里熟透的蕃茄\n[03:22.82]你突然对我说七里香的名字很美\n[03:29.27]我此刻却只想亲吻你倔强的嘴\n[03:35.97]雨下整夜我的爱溢出就像雨水\n[03:42.72]院子落叶跟我的思念厚厚一叠\n[03:49.43]几句是非也无法将我的热情冷却\n[03:56.90]你出现在我诗的每一页\n[04:02.76]\n[04:03.50]整夜我的爱溢出就像雨水\n[04:09.58]窗台蝴蝶像诗里纷飞的美丽章节\n[04:16.66]我接着写\n[04:18.42]\n[04:18.93]把永远爱你写进诗的结尾\n[04:24.01]你是我唯一想要的了解",
        "url": "http://dl.stream.qqmusic.qq.com/M500004Z8Ihr0JIu5s.mp3?vkey=19F8CB473A1B2F83716934DDBC8F77202D2AD85C7374B30292F4062B4E21CFAFB8240208BC5C7671756C611572983CE750905643F966B8BD&guid=5150825362&fromtag=1",
        "pic": "http://y.gtimg.cn/music/photo_new/T002R300x300M000003DFRzD192KKD.jpg"
    },
    {
        "type": "qq",
        "link": "http://y.qq.com/n/yqq/song/004emQMs09Z1lz.html",
        "songid": "004emQMs09Z1lz",
        "title": "烟花易冷",
        "author": "周杰伦",
        "lrc": "[ti:烟花易冷]\n[ar:周杰伦]\n[al:263287]\n[by:]\n[offset:0]\n[00:00.00]烟花易冷 - 周杰伦 (Jay Chou)\n[00:02.87]词：方文山\n[00:05.74]曲：周杰伦\n[00:08.62]编曲：黄雨勋\n[00:11.49]繁华声 遁入空门 折煞了世人\n[00:16.54]\n[00:17.55]梦偏冷 辗转一生 情债又几本\n[00:23.10]\n[00:23.99]如你默认 生死枯等\n[00:29.29]\n[00:29.99]枯等一圈 又一圈的 年轮\n[00:36.55]浮屠塔 断了几层 断了谁的魂\n[00:41.85]\n[00:42.43]痛直奔 一盏残灯 倾塌的山门\n[00:48.42]\n[00:48.93]容我再等 历史转身\n[00:54.10]\n[00:55.37]等酒香醇 等你弹 一曲古筝\n[01:01.55]雨纷纷 旧故里草木深\n[01:06.54]\n[01:07.87]我听闻 你始终一个人\n[01:12.82]\n[01:14.02]斑驳的城门 盘踞着老树根\n[01:20.15]石板上回荡的是 再等\n[01:25.26]\n[01:26.46]雨纷纷 旧故里草木深\n[01:31.45]\n[01:32.96]我听闻 你仍守着孤城\n[01:38.01]\n[01:39.02]城郊牧笛声 落在那座野村\n[01:45.21]缘份落地生根是 我们\n[01:50.13]\n[01:54.40]听青春 迎来笑声 羡煞许多人\n[01:59.57]\n[02:00.40]那史册 温柔不肯 下笔都太狠\n[02:06.71]烟花易冷 人事易分\n[02:12.01]\n[02:12.84]而你在问 我是否还 认真\n[02:18.39]\n[02:19.02]千年后 累世情深 还有谁在等\n[02:25.33]而青史 岂能不真 魏书洛阳城\n[02:31.84]如你在跟 前世过门\n[02:36.95]\n[02:38.15]跟着红尘 跟随我 浪迹一生\n[02:43.20]\n[02:44.40]雨纷纷 旧故里草木深\n[02:49.38]\n[02:50.65]我听闻 你始终一个人\n[02:55.70]\n[02:56.90]斑驳的城门 盘踞着老树根\n[03:03.08]石板上回荡的是 再等\n[03:09.34]雨纷纷 旧故里草木深\n[03:14.32]\n[03:15.52]我听闻 你仍守着孤城\n[03:21.32]\n[03:21.90]城郊牧笛声 落在那座野村\n[03:28.02]缘份落地生根是 我们\n[03:33.82]\n[03:35.01]雨纷纷 旧故里草木深\n[03:36.61]我听闻 你始终一个人\n[03:38.59]斑驳的城门 盘踞着老树根\n[03:40.35]石板上回荡的是 再等\n[03:41.86]雨纷纷 雨纷纷 旧故里草木深\n[03:45.02]我听闻 我听闻 你仍守着孤城\n[03:47.61]城郊牧笛声 落在那座野村\n[03:53.32]缘份落地生根是 我们\n[03:58.17]\n[03:59.58]缘份落地生根是 我们\n[04:04.36]\n[04:05.77]伽蓝寺听雨声盼 永恒",
        "url": "http://dl.stream.qqmusic.qq.com/M500004emQMs09Z1lz.mp3?vkey=19F8CB473A1B2F83716934DDBC8F77202D2AD85C7374B30292F4062B4E21CFAFB8240208BC5C7671756C611572983CE750905643F966B8BD&guid=5150825362&fromtag=1",
        "pic": "http://y.gtimg.cn/music/photo_new/T002R300x300M000000bviBl4FjTpO.jpg"
    },
    {
        "type": "qq",
        "link": "http://y.qq.com/n/yqq/song/003xv4w313tZHV.html",
        "songid": "003xv4w313tZHV",
        "title": "红尘客栈",
        "author": "周杰伦",
        "lrc": "[ti:红尘客栈]\n[ar:周杰伦]\n[al:十二新作]\n[by:]\n[offset:0]\n[00:00.00]红尘客栈 - 周杰伦 (Jay Chou)\n[00:07.42]词：方文山\n[00:14.84]曲：周杰伦\n[00:22.27]天涯的尽头是风沙\n[00:25.79]\n[00:27.49]红尘的故事叫牵挂\n[00:31.26]\n[00:32.75]封刀隐没在寻常人家 东篱下\n[00:37.50]\n[00:38.45]闲云野鹤古刹\n[00:41.82]\n[00:43.78]快马在江湖里厮杀\n[00:47.02]\n[00:48.77]无非是名跟利放不下\n[00:52.67]\n[00:54.08]心中有江山的人岂能快意潇洒\n[00:59.07]\n[00:59.73]我只求与你共华发\n[01:03.18]\n[01:07.10]剑出鞘恩怨了 谁笑\n[01:10.77]\n[01:11.76]我只求今朝拥你 入怀抱\n[01:16.40]\n[01:17.12]红尘客栈风似刀 骤雨落宿命敲\n[01:25.34]\n[01:26.49]任武林谁领风骚\n[01:29.04]我却只为你折腰\n[01:32.24]\n[01:33.10]过荒村野桥寻世外古道\n[01:37.57]\n[01:38.42]远离人间尘嚣\n[01:41.01]柳絮飘执子之手逍遥\n[01:46.00]\n[02:06.34]檐下窗棂斜映枝桠\n[02:10.05]\n[02:11.60]与你席地对座饮茶\n[02:15.33]\n[02:16.85]我以工笔画将你牢牢的记下\n[02:21.81]\n[02:22.42]提笔不为风雅\n[02:25.56]\n[02:27.76]灯下叹红颜近晚霞\n[02:31.04]\n[02:32.47]我说缘份一如参禅不说话\n[02:36.64]\n[02:37.88]你泪如梨花洒满了纸上的天下\n[02:42.98]\n[02:43.75]爱恨如写意山水画\n[02:48.58]\n[02:51.33]剑出鞘恩怨了 谁笑\n[02:54.83]\n[02:55.73]我只求今朝拥你入怀抱\n[03:00.52]\n[03:01.11]红尘客栈风似刀 骤雨落宿命敲\n[03:10.45]任武林谁领风骚\n[03:12.80]我却只为你折腰\n[03:16.24]\n[03:17.03]过荒村野桥寻世外古道\n[03:21.60]\n[03:22.40]远离人间尘嚣\n[03:25.06]柳絮飘执子之手逍遥\n[03:29.72]\n[03:48.12]任武林谁领风骚\n[03:50.13]我却只为你折腰\n[03:53.69]\n[03:54.35]你回眸多娇我泪中带笑\n[03:59.80]酒招旗风中萧萧 剑出鞘恩怨了",
        "url": "http://dl.stream.qqmusic.qq.com/M500003xv4w313tZHV.mp3?vkey=19F8CB473A1B2F83716934DDBC8F77202D2AD85C7374B30292F4062B4E21CFAFB8240208BC5C7671756C611572983CE750905643F966B8BD&guid=5150825362&fromtag=1",
        "pic": "http://y.gtimg.cn/music/photo_new/T002R300x300M000003Ow85E3pnoqi.jpg"
    },
    {
        "type": "qq",
        "link": "http://y.qq.com/n/yqq/song/0009BCJK1nRaad.html",
        "songid": "0009BCJK1nRaad",
        "title": "简单爱",
        "author": "周杰伦",
        "lrc": "[ti:简单爱]\n[ar:周杰伦]\n[al:范特西]\n[by:]\n[offset:0]\n[00:00.00]简单爱 - 周杰伦 (Jay Chou)\n[00:06.73]词：徐若瑄\n[00:13.47]曲：周杰伦\n[00:20.20]编曲：林迈可\n[00:26.94]说不上为什么 我变得很主动\n[00:30.79]\n[00:31.66]若爱上一个人 什么都会值得去做\n[00:36.65]我想大声宣布 对你依依不舍\n[00:41.08]\n[00:41.65]连隔壁邻居都猜到我现在的感受\n[00:46.08]\n[00:46.64]河边的风 在吹着头发 飘动\n[00:51.59]牵着你的手 一阵莫名感动\n[00:56.46]我想带你 回我的外婆家\n[01:00.39]一起看着日落 一直到我们都睡着\n[01:05.89]\n[01:06.70]我想就这样牵着你的手不放开\n[01:11.25]爱能不能够永远单纯没有悲哀\n[01:15.93]我 想带你骑单车\n[01:18.37]我 想和你看棒球\n[01:20.92]想这样没担忧\n[01:23.48]唱着歌 一直走\n[01:25.66]\n[01:26.23]我想就这样牵着你的手不放开\n[01:31.03]爱可不可以简简单单没有伤害\n[01:35.65]你 靠着我的肩膀\n[01:38.21]你 在我胸口睡着\n[01:40.58]\n[01:41.48]像这样的生活\n[01:43.35]我爱你 你爱我\n[01:45.98]想 简简单单 爱\n[01:50.65]\n[01:55.47]想 简简单单 爱\n[02:01.71]\n[02:06.08]我想大声宣布 对你依依不舍\n[02:10.70]连隔壁邻居都猜到我现在的感受\n[02:15.75]河边的风 在吹着头发 飘动\n[02:20.25]牵着你的手 一阵莫名感动\n[02:25.36]我想带你 回我的外婆家\n[02:29.48]一起看着日落 一直到我们都睡着\n[02:35.16]我想就这样牵着你的手不放开\n[02:40.15]爱能不能够永远单纯没有悲哀\n[02:45.02]我 想带你骑单车\n[02:47.45]我 想和你看棒球\n[02:50.01]想这样没担忧\n[02:52.50]唱着歌 一直走\n[02:55.19]我想就这样牵着你的手不放开\n[03:00.18]爱可不可以简简单单没有伤害\n[03:04.86]你 靠着我的肩膀\n[03:07.30]你 在我胸口睡着\n[03:09.85]像这样的生活\n[03:12.22]我爱你 你爱我\n[03:14.60]\n[03:15.43]想 简简单单 爱\n[03:20.92]\n[03:24.44]想 简简单单 爱\n[03:30.18]\n[03:35.17]我想就这样牵着你的手不放开\n[03:39.73]爱能不能够永远单纯没有悲哀\n[03:44.47]我 想带你骑单车\n[03:46.84]我 想和你看棒球\n[03:49.34]想这样没担忧\n[03:51.99]唱着歌 一直走\n[03:54.05]\n[03:54.61]我想就这样牵着你的手不放开\n[03:59.48]爱可不可以简简单单没有伤害\n[04:04.16]你 靠着我的肩膀\n[04:06.59]你 在我胸口睡着\n[04:09.15]像这样的生活\n[04:11.67]我爱你 你爱我",
        "url": "http://dl.stream.qqmusic.qq.com/M5000009BCJK1nRaad.mp3?vkey=19F8CB473A1B2F83716934DDBC8F77202D2AD85C7374B30292F4062B4E21CFAFB8240208BC5C7671756C611572983CE750905643F966B8BD&guid=5150825362&fromtag=1",
        "pic": "http://y.gtimg.cn/music/photo_new/T002R300x300M000000I5jJB3blWeN.jpg"
    },
    {
        "type": "qq",
        "link": "http://y.qq.com/n/yqq/song/002CUU2B3WuGLc.html",
        "songid": "002CUU2B3WuGLc",
        "title": "Mine Mine",
        "author": "周杰伦",
        "lrc": "[ti:Mine Mine]\n[ar:周杰伦]\n[al:惊叹号]\n[by:]\n[offset:0]\n[00:00.00]Mine Mine - 周杰伦 (Jay Chou)\n[00:06.33]词：周杰伦\n[00:12.67]曲：周杰伦\n[00:19.01]没有你的生活\n[00:20.39]\n[00:20.90]我开始写小说\n[00:23.08]好多画面好多灵感\n[00:25.10]我要把稿费都给你\n[00:27.38]巷口不小心经过\n[00:29.09]你的车子依旧停在红线 帮你缴罚单\n[00:32.40]你叫我别管 我才想到我们已经分开\n[00:35.85]想起那一个夏天\n[00:37.89]那不是那不是那是冬天\n[00:40.05]想起你生气的脸\n[00:41.97]每天就像冬天 唉唉唉\n[00:47.23]你说那是爱爱爱\n[00:51.05]\n[00:52.92]谁该坚强起来\n[00:54.93]月亮还是太阳\n[00:57.05]是谁遮了谁\n[00:58.95]是谁都会依赖\n[01:00.82]\n[01:01.35]你说已分开 为什么还要帮你撑伞\n[01:07.80]\n[01:08.47]Cuz baby you are mine mine (Mine)\n[01:13.81]Mine mine (Mine)\n[01:17.43]\n[01:18.20]太快 就承认 我真的很想你\n[01:23.58]会不会没有男子气概 You say\n[01:26.48]Bye-bye (Bye)\n[01:30.18]Oh bye-bye (Bye)\n[01:34.06]\n[01:35.18]拆开 我的心随你看\n[01:39.07]\n[01:41.86]满满的都是爱\n[01:46.34]\n[01:47.95]我的眼皮跳一下\n[01:50.34]代表你在想我\n[01:51.97]我的耳朵痒一下\n[01:54.07]代表你在讲我坏话\n[01:56.24]我没这么不好吧\n[01:58.56]不用跟朋友说吧\n[02:00.75]如果以后和好了\n[02:02.38]看到你朋友不是很尴尬\n[02:04.56]\n[02:05.10]想起那一个夏天\n[02:07.12]那不是那不是那是冬天\n[02:09.26]想起你生气的脸\n[02:11.17]每天就像冬天 唉唉唉\n[02:15.82]\n[02:16.40]你说那是爱爱爱\n[02:20.40]\n[02:22.21]骗谁 我说的气话都收回\n[02:25.14]我写的小说根本是空白黑夜\n[02:28.59]\n[02:29.20]你说既然已分开 为何还要帮你撑伞\n[02:38.16]\n[02:38.94]唛唛 你唛搁唛搁偷偷离开\n[02:42.94]唛唛 你唛搁唛搁偷偷离开\n[02:47.27]唛惊 我不会放你一人治那\n[02:51.78]\n[02:52.81]你想祙有人靠有人会疼\n[02:55.82]唛呐 你雨伞雨伞赶紧打开\n[02:59.90]唛呐 你雨伞雨伞赶紧打开\n[03:04.28]唛闹 落大雨你淋雨我艰苦\n[03:09.91]落大雨我没你会艰苦\n[03:13.23]\n[03:28.76]Cuz baby you are mine mine (Mine)\n[03:33.75]Minemine (Mine)\n[03:37.51]\n[03:38.18]太快 就承认 我真的很想你\n[03:43.73]会不会没有男子气概 You say\n[03:46.74]唛呐 你雨伞雨伞赶紧打开\n[03:50.99]唛呐 你雨伞雨伞赶紧打开\n[03:55.19]唛闹 落大雨你淋雨我艰苦\n[03:59.47]\n[04:01.01]落大雨我没你会艰苦",
        "url": "http://dl.stream.qqmusic.qq.com/M500002CUU2B3WuGLc.mp3?vkey=19F8CB473A1B2F83716934DDBC8F77202D2AD85C7374B30292F4062B4E21CFAFB8240208BC5C7671756C611572983CE750905643F966B8BD&guid=5150825362&fromtag=1",
        "pic": "http://y.gtimg.cn/music/photo_new/T002R300x300M000003KNcyk0t3mwg.jpg"
    },
    {
        "type": "qq",
        "link": "http://y.qq.com/n/yqq/song/004BhQke4adHcf.html",
        "songid": "004BhQke4adHcf",
        "title": "给我一首歌的时间",
        "author": "周杰伦",
        "lrc": "[ti:给我一首歌的时间]\n[ar:周杰伦]\n[al:魔杰座]\n[by:]\n[offset:0]\n[00:00.00]给我一首歌的时间 - 周杰伦 (Jay Chou)\n[00:04.60]词：周杰伦\n[00:09.21]曲：周杰伦\n[00:13.81]编曲：林迈可\n[00:18.42]雨淋湿了天空 毁得很讲究\n[00:22.60]你说你不懂 为何在这时牵手\n[00:26.03]\n[00:26.61]我晒干了沉默 悔得很冲动\n[00:30.71]就算这是做错 也只是怕错过\n[00:35.10]在一起叫梦 分开了叫痛\n[00:39.14]是不是说 没有做完的梦最痛\n[00:43.15]迷路的后果 我能承受\n[00:46.40]这最后的出口 在爱过了才有\n[00:52.29]\n[00:53.38]能不能给我一首歌的时间\n[00:57.37]紧紧的把那拥抱变成永远\n[01:01.44]在我的怀里你不用害怕失眠\n[01:05.46]哦 如果你想忘记我也能失忆\n[01:09.06]\n[01:09.60]能不能给我一首歌的时间\n[01:13.61]把故事听到最后才说再见\n[01:17.72]你送我的眼泪 让它留在雨天\n[01:21.69]哦 越过你划的线\n[01:23.93]我定了勇气的终点\n[01:28.96]\n[01:31.80]雨淋湿了天空 毁得很讲究\n[01:35.70]你说你不懂 我为何在这时牵手\n[01:39.16]\n[01:39.73]我晒干了沉默 悔得很冲动\n[01:43.99]就算这是做错 也只是怕错过\n[01:48.30]在一起叫梦 分开了叫痛\n[01:52.31]是不是说 没有做完的梦最痛\n[01:56.33]迷路的后果 我能承受\n[01:59.60]这最后的出口 在爱过了才有\n[02:06.59]能不能给我一首歌的时间\n[02:10.57]紧紧的把那拥抱变成永远\n[02:14.64]在我的怀里你不用害怕失眠\n[02:18.67]哦 如果你想忘记我也能失忆\n[02:22.79]能不能给我一首歌的时间\n[02:26.87]把故事听到最后才说再见\n[02:30.91]你送我的眼泪 让它留在雨天\n[02:34.98]哦 越过你划的线\n[02:37.18]我定了勇气的终点\n[02:42.50]\n[02:43.16]哦 你说我不该 不该\n[02:45.87]不该在这时候说了我爱你\n[02:50.97]\n[02:52.49]要怎么证明我没有说谎的力气\n[02:59.49]哦 请告诉我暂停算不算放弃\n[03:07.46]\n[03:08.78]我只有一天的回忆\n[03:15.16]\n[03:15.67]能不能给我一首歌的时间\n[03:19.68]紧紧的把那拥抱变成永远\n[03:23.79]在我的怀里你不用害怕失眠\n[03:27.83]哦 如果你想忘记我也能失忆\n[03:31.42]\n[03:32.05]能不能给我一首歌的时间\n[03:36.01]把故事听到最后\n[03:37.57]把故事听到最后才说再见\n[03:39.99]\n[03:40.68]你送我的眼泪 让它留在雨天\n[03:44.16]\n[03:44.74]哦 越过你划的线\n[03:46.54]我定了勇气的终点\n[03:50.09]你说我不该 不该\n[03:51.45]不该在这时说了爱你\n[03:53.52]要怎么证明我没力气\n[03:55.81]告诉我暂停算不算放弃\n[03:57.77]你说我不该 不该\n[03:59.54]不该在这时才说爱你\n[04:01.63]要怎么证明我没有力气\n[04:03.99]我只有一天的回忆",
        "url": "http://dl.stream.qqmusic.qq.com/M500004BhQke4adHcf.mp3?vkey=19F8CB473A1B2F83716934DDBC8F77202D2AD85C7374B30292F4062B4E21CFAFB8240208BC5C7671756C611572983CE750905643F966B8BD&guid=5150825362&fromtag=1",
        "pic": "http://y.gtimg.cn/music/photo_new/T002R300x300M000002Neh8l0uciQZ.jpg"
    },
    {
        "type": "qq",
        "link": "http://y.qq.com/n/yqq/song/003iY6cU4YG0xi.html",
        "songid": "003iY6cU4YG0xi",
        "title": "黑色毛衣",
        "author": "周杰伦",
        "lrc": "[ti:黑色毛衣]\n[ar:周杰伦]\n[al:十一月的萧邦]\n[by:]\n[offset:0]\n[00:00.00]黑色毛衣 - 周杰伦 (Jay Chou)\n[00:06.22]词：周杰伦\n[00:12.44]曲：周杰伦\n[00:18.67]一件黑色毛衣 两个人的回忆\n[00:24.86]\n[00:26.79]雨过之后 更难忘记\n[00:29.92]\n[00:32.53]忘记我还爱你\n[00:34.22]\n[00:35.03]你不用在意 流泪也只是刚好而已\n[00:42.77]\n[00:43.40]我早已经待在谷底\n[00:46.47]\n[00:49.84]我知道不能再留住你\n[00:52.77]\n[00:53.33]也知道不能没有骨气\n[00:56.96]\n[00:58.27]感激你 让我拥有秋天的美丽\n[01:02.63]\n[01:05.32]看着那白色的蜻蜓\n[01:08.75]\n[01:09.49]在空中忘了前进\n[01:13.68]还能不能 重新编织\n[01:16.80]\n[01:17.73]脑海中起毛球的记忆\n[01:21.98]\n[01:22.72]再说我爱你 可能雨也不会停\n[01:29.78]黑色毛衣 藏在哪里\n[01:34.02]\n[01:34.62]就让回忆永远停在那里\n[01:39.29]\n[01:58.01]一件黑色毛衣 两个人的回忆\n[02:04.44]\n[02:06.13]雨过之后 更难忘记\n[02:09.50]\n[02:12.12]忘记我还爱你\n[02:13.74]\n[02:14.68]你不用在意 流泪也只是刚好而已\n[02:22.79]我早已经待在谷底\n[02:26.28]\n[02:29.16]我知道不能再留住你\n[02:32.40]\n[02:32.96]也知道不能没有骨气\n[02:36.39]\n[02:37.45]感激你 让我拥有秋天的美丽\n[02:42.37]\n[02:44.81]看着那白色的蜻蜓\n[02:48.56]\n[02:49.24]在空中忘了前进\n[02:52.42]\n[02:53.24]还能不能 重新编织\n[02:57.30]脑海中起毛球的记忆\n[03:02.48]再说我爱你 可能雨也不会停\n[03:09.52]黑色毛衣 藏在哪里\n[03:14.02]\n[03:14.84]就让回忆永远停在那里\n[03:18.89]\n[03:19.71]看着那白色的蜻蜓\n[03:23.83]在空中忘了前进\n[03:26.51]\n[03:27.26]还能不能 重新编织\n[03:30.51]脑海中起毛球的记忆\n[03:34.18]\n[03:35.18]再说我爱你 可能雨也不会停\n[03:41.11]\n[03:42.05]黑色毛衣 藏在哪里\n[03:45.35]\n[03:46.35]就让回忆永远停在那里",
        "url": "http://dl.stream.qqmusic.qq.com/M500003iY6cU4YG0xi.mp3?vkey=19F8CB473A1B2F83716934DDBC8F77202D2AD85C7374B30292F4062B4E21CFAFB8240208BC5C7671756C611572983CE750905643F966B8BD&guid=5150825362&fromtag=1",
        "pic": "http://y.gtimg.cn/music/photo_new/T002R300x300M0000024bjiL2aocxT.jpg"
    },
    {
        "type": "qq",
        "link": "http://y.qq.com/n/yqq/song/003ZrdgZ0UnjDl.html",
        "songid": "003ZrdgZ0UnjDl",
        "title": "最长的电影",
        "author": "周杰伦",
        "lrc": "[ti:最长的电影]\n[ar:周杰伦]\n[al:我很忙]\n[by:]\n[offset:0]\n[00:00.00]最长的电影 - 周杰伦 (Jay Chou)\n[00:03.07]词：周杰伦\n[00:06.15]曲：周杰伦\n[00:09.22]编曲：钟兴民\n[00:12.30]制作人：周杰伦\n[00:15.38]我们的开始\n[00:18.22]\n[00:19.16]是很长的电影\n[00:22.26]\n[00:23.50]放映了三年\n[00:26.09]\n[00:26.92]我票都还留着\n[00:30.01]\n[00:31.49]冰上的芭蕾\n[00:34.17]\n[00:34.87]脑海中还在旋转\n[00:38.82]\n[00:40.28]望着你 慢慢忘记你\n[00:45.08]\n[00:47.37]朦胧的时间\n[00:49.96]\n[00:51.27]我们溜了多远\n[00:53.96]\n[00:55.24]冰刀划的圈\n[00:57.93]\n[00:58.65]圈起了谁改变\n[01:01.97]\n[01:02.87]如果再重来\n[01:05.91]\n[01:06.89]会不会稍嫌狼狈\n[01:11.00]\n[01:11.85]爱是不是不开口才珍贵\n[01:18.29]再给我两分钟\n[01:22.30]让我把记忆结成冰\n[01:26.18]别融化了眼泪\n[01:29.22]你妆都花了要我怎么记得\n[01:34.17]记得你叫我忘了吧\n[01:38.26]记得你叫我忘了吧\n[01:42.15]\n[01:42.94]你说你会哭\n[01:45.22]不是因为在乎\n[01:49.29]\n[02:02.52]朦胧的时间\n[02:05.41]\n[02:06.36]我们溜了多远\n[02:09.43]\n[02:10.33]冰刀划的圈\n[02:13.78]圈起了谁改变\n[02:18.12]如果再重来\n[02:21.16]\n[02:22.07]会不会稍嫌狼狈\n[02:27.14]爱是不是不开口才珍贵\n[02:33.08]\n[02:33.62]再给我两分钟\n[02:37.67]让我把记忆结成冰\n[02:41.59]别融化了眼泪\n[02:44.65]你妆都花了要我怎么记得\n[02:49.59]记得你叫我忘了吧\n[02:53.62]记得你叫我忘了吧\n[02:57.86]\n[02:58.52]你说你会哭\n[03:00.57]不是因为在乎\n[03:05.43]再给我两分钟\n[03:09.38]让我把记忆结成冰\n[03:13.33]别融化了眼泪\n[03:16.37]你妆都花了要我怎么记得\n[03:21.30]记得你叫我忘了吧\n[03:25.32]记得你叫我忘了吧\n[03:29.97]\n[03:32.26]你说你会哭\n[03:34.34]不是因为在乎",
        "url": "http://dl.stream.qqmusic.qq.com/M500003ZrdgZ0UnjDl.mp3?vkey=19F8CB473A1B2F83716934DDBC8F77202D2AD85C7374B30292F4062B4E21CFAFB8240208BC5C7671756C611572983CE750905643F966B8BD&guid=5150825362&fromtag=1",
        "pic": "http://y.gtimg.cn/music/photo_new/T002R300x300M000002eFUFm2XYZ7z.jpg"
    },
    {
        "type": "qq",
        "link": "http://y.qq.com/n/yqq/song/002u8ZOM4C7QF4.html",
        "songid": "002u8ZOM4C7QF4",
        "title": "手写的从前",
        "author": "周杰伦",
        "lrc": "[ti:08-手写的从前]\n[ar:是]\n[al:]\n[by:]\n[offset:0]\n[00:00.00]手写的从前 (优酸乳为爱告白广告曲) - 周杰伦 (Jay Chou)\n[00:03.68]词：方文山\n[00:07.37]曲：周杰伦\n[00:11.06]这风铃跟心动很接近\n[00:15.15]\n[00:16.22]这封信还在怀念旅行\n[00:20.43]\n[00:21.26]路过的爱情都太年轻\n[00:25.45]你是我想要 再回去的风景\n[00:30.62]\n[00:31.51]这别离被瓶装成秘密\n[00:35.98]这雏菊美得像诗句\n[00:39.07]而我在风中等你 的消息\n[00:44.20]等月光落雪地\n[00:47.22]\n[00:48.47]等枫红染秋季等相遇\n[00:52.21]\n[00:52.82]我重温午后的阳光\n[00:58.00]将吉他斜背在肩上\n[01:02.86]跟多年前一样 我们轻轻地唱\n[01:07.92]去任何地方\n[01:10.91]\n[01:14.33]我看着你的脸 轻刷着和弦\n[01:19.66]情人节卡片 手写的永远\n[01:23.81]还记得广场公园 一起表演\n[01:28.95]校园旁糖果店 记忆里在微甜\n[01:34.66]我看着你的脸 轻刷着和弦\n[01:40.08]初恋是整遍 手写的从前\n[01:44.07]还记得那年秋天 说了再见\n[01:49.26]当恋情已走远\n[01:51.88]我将你深埋在 心里面\n[01:56.18]\n[02:15.82]微风需要竹林 溪流需要蜻蜓\n[02:18.34]乡愁般的离开 需要片片浮萍\n[02:20.93]记得那年的雨季 回忆里特安静\n[02:23.66]哭过后的决定 是否还能进行\n[02:26.31]我傻傻等待 傻傻等春暖花开\n[02:28.68]等终等于等明等白 等爱情回来\n[02:31.14]青春属于表白 阳光属于窗台\n[02:33.69]而我想我属于\n[02:34.75]一个拥有你的未来\n[02:36.35]纸上的彩虹 用素描画的钟\n[02:38.91]我还在修改 回忆之中你的笑容\n[02:41.43]该怎么去形容 为思念酝酿的痛\n[02:43.96]夜空霓虹 都是我不要的繁荣\n[02:46.45]或许去趟沙滩 或许去看看夕阳\n[02:48.97]或许任何一个可以想心事的地方\n[02:51.67]情绪在咖啡馆 被调成一篇文章\n[02:54.27]彻底爱上你如诗一般透明的泪光\n[02:56.65]我看着你的脸 轻刷着和弦\n[03:00.85]\n[03:01.77]情人节卡片 手写的永远\n[03:05.92]还记得广场公园 一起表演\n[03:11.02]校园旁糖果店 记忆里在微甜\n[03:16.76]我看着你的脸 轻刷着和弦\n[03:22.18]初恋是整遍 手写的从前\n[03:26.23]还记得那年秋天 说了再见\n[03:31.36]当恋情已走远\n[03:33.89]我将你深埋在 心里面\n[03:38.10]\n[03:38.74]我重温午后的阳光\n[03:43.23]\n[03:43.88]将吉他斜背在肩上\n[03:48.71]跟多年前一样 我们轻轻地唱\n[03:53.83]去任何地方\n[03:57.78]\n[04:00.28]我看着你的脸 轻刷着和弦\n[04:05.64]情人节卡片 手写的永远\n[04:09.76]还记得广场公园 一起表演\n[04:14.76]校园旁糖果店 记忆里在微甜\n[04:20.58]我看着你的脸 轻刷着和弦\n[04:25.17]\n[04:25.98]初恋是整遍 手写的从前\n[04:30.15]还记得那年秋天 说了再见\n[04:35.19]当恋情已走远\n[04:37.78]我将你深埋在 心里面",
        "url": "http://dl.stream.qqmusic.qq.com/M500002u8ZOM4C7QF4.mp3?vkey=19F8CB473A1B2F83716934DDBC8F77202D2AD85C7374B30292F4062B4E21CFAFB8240208BC5C7671756C611572983CE750905643F966B8BD&guid=5150825362&fromtag=1",
        "pic": "http://y.gtimg.cn/music/photo_new/T002R300x300M000001uqejs3d6EID.jpg"
    },
    {
        "type": "qq",
        "link": "http://y.qq.com/n/yqq/song/0027oMO61wWi55.html",
        "songid": "0027oMO61wWi55",
        "title": "发如雪",
        "author": "周杰伦",
        "lrc": "[ti:发如雪]\n[ar:周杰伦]\n[al:十一月的萧邦]\n[by:]\n[offset:0]\n[00:00.00]发如雪 (Snowy hair) - 周杰伦 (Jay Chou)\n[00:07.35]词：方文山\n[00:14.70]曲：周杰伦\n[00:22.05]狼牙月 伊人憔悴\n[00:26.17]我举杯 饮尽了风雪\n[00:31.36]\n[00:32.07]是谁打翻前世柜 惹尘埃是非\n[00:38.57]缘字诀 几番轮回\n[00:42.73]你锁眉 哭红颜唤不回\n[00:47.79]\n[00:48.65]纵然青史已经成灰 我爱不灭\n[00:55.51]\n[00:56.17]繁华如三千东流水\n[00:59.66]\n[01:00.27]我只取一瓢爱了解\n[01:03.86]\n[01:04.38]只恋你化身的蝶\n[01:10.06]你发如雪 凄美了离别\n[01:14.64]我焚香感动了谁\n[01:19.39]邀明月 让回忆皎洁\n[01:23.54]爱在月光下完美\n[01:26.60]你发如雪 纷飞了眼泪\n[01:31.19]我等待苍老了谁\n[01:35.91]红尘醉 微醺的岁月\n[01:40.32]我用无悔 刻永世爱你的碑\n[01:44.68]你发如雪 凄美了离别\n[01:47.13]我焚香感动了谁\n[01:48.90]邀明月 让回忆皎洁\n[01:51.14]爱在月光下完美\n[01:53.04]你发如雪 纷飞了眼泪\n[01:55.31]我等待苍老了谁\n[01:57.15]红尘醉 微醺的岁月\n[01:59.70]\n[02:01.34]狼牙月 伊人憔悴\n[02:05.39]我举杯 饮尽了风雪\n[02:10.60]\n[02:11.37]是谁打翻前世柜 惹尘埃是非\n[02:17.84]缘字诀 几番轮回\n[02:22.00]你锁眉 哭红颜唤不回\n[02:27.10]\n[02:27.89]纵然青史已经成灰 我爱不灭\n[02:34.87]\n[02:35.42]繁华如三千东流水\n[02:39.02]\n[02:39.55]我只取一瓢爱了解\n[02:43.07]\n[02:43.68]只恋你化身的蝶\n[02:49.36]你发如雪 凄美了离别\n[02:53.96]我焚香感动了谁\n[02:58.70]邀明月 让回忆皎洁\n[03:02.77]爱在月光下完美\n[03:05.94]你发如雪 纷飞了眼泪\n[03:10.49]我等待苍老了谁\n[03:15.26]红尘醉 微醺的岁月\n[03:19.64]我用无悔 刻永世爱你的碑\n[03:23.96]你发如雪 凄美了离别\n[03:26.34]我焚香感动了谁\n[03:28.36]邀明月 让回忆皎洁\n[03:30.44]爱在月光下完美\n[03:32.34]你发如雪 纷飞了眼泪\n[03:34.60]我等待苍老了谁\n[03:36.68]红尘醉 微醺的岁月\n[03:38.93]你发如雪 凄美了离别\n[03:43.63]我焚香感动了谁\n[03:48.26]邀明月 让回忆皎洁\n[03:52.47]爱在月光下完美\n[03:55.59]你发如雪 纷飞了眼泪\n[04:00.16]我等待苍老了谁\n[04:04.51]红尘醉 微醺的岁月\n[04:09.33]我用无悔 刻永世爱你的碑\n[04:16.36]啦儿啦儿啦\n[04:18.27]啦儿啦 啦儿啦 啦儿啦儿啊\n[04:22.42]铜镜映无邪 扎马尾\n[04:26.12]你若撒野 今生我把酒奉陪\n[04:30.25]\n[04:30.78]啦儿啦 啦儿啦 啦儿啦儿啦\n[04:34.24]\n[04:34.89]啦儿啦 啦儿啦 啦儿啦儿啊\n[04:38.42]\n[04:39.03]铜镜映无邪 扎马尾\n[04:42.67]你若撒野 今生我把酒奉陪",
        "url": "http://dl.stream.qqmusic.qq.com/M5000027oMO61wWi55.mp3?vkey=19F8CB473A1B2F83716934DDBC8F77202D2AD85C7374B30292F4062B4E21CFAFB8240208BC5C7671756C611572983CE750905643F966B8BD&guid=5150825362&fromtag=1",
        "pic": "http://y.gtimg.cn/music/photo_new/T002R300x300M0000024bjiL2aocxT.jpg"
    },
    {
        "type": "qq",
        "link": "http://y.qq.com/n/yqq/song/002MXZNu1GToOk.html",
        "songid": "002MXZNu1GToOk",
        "title": "不能说的秘密",
        "author": "周杰伦",
        "lrc": "[ti:不能说的秘密]\n[ar:周杰伦]\n[al:不能说的秘密 电影原声带]\n[by:]\n[offset:0]\n[00:00.00]不能说的秘密 (《不能说的秘密》电影插曲) - 周杰伦 (Jay Chou)\n[00:03.51]词：方文山\n[00:07.03]曲：周杰伦\n[00:10.55]编曲：林迈可\n[00:14.07]冷咖啡离开了杯垫\n[00:17.06]我忍住的情绪在很后面\n[00:21.18]\n[00:27.17]拼命想挽回的从前\n[00:30.16]在我脸上依旧清晰可见\n[00:34.40]\n[00:40.71]最美的不是下雨天\n[00:43.02]\n[00:43.64]是曾与你躲过雨的屋檐\n[00:47.76]\n[00:52.81]回忆的画面 在荡着秋千\n[00:59.24]梦开始不甜\n[01:01.19]\n[01:05.32]你说把爱渐渐放下会走更远\n[01:10.86]\n[01:11.60]又何必去改变 已错过的时间\n[01:17.62]\n[01:18.36]你用你的指尖阻止我说再见\n[01:24.98]想象你在身边 在完全失去之前\n[01:30.97]\n[01:31.66]你说把爱渐渐放下会走更远\n[01:38.27]或许命运的签 只让我们遇见\n[01:44.93]只让我们相恋这一季的秋天\n[01:51.60]飘落后才发现 这幸福的碎片\n[01:58.27]要我怎么捡\n[02:01.22]\n[02:27.49]冷咖啡离开了杯垫\n[02:29.89]\n[02:30.50]我忍住的情绪在很后面\n[02:34.82]\n[02:40.81]拼命想挽回的从前\n[02:43.01]\n[02:43.71]在我脸上依旧清晰可见\n[02:47.88]\n[02:54.12]最美的不是下雨天\n[02:56.36]\n[02:56.99]是曾与你躲过雨的屋檐\n[03:01.11]\n[03:06.35]回忆的画面 在荡着秋千\n[03:12.59]梦开始不甜\n[03:14.53]\n[03:18.76]你说把爱渐渐放下会走更远\n[03:24.28]\n[03:25.02]又何必去改变 已错过的时间\n[03:31.64]你用你的指尖阻止我说再见\n[03:38.38]想象你在身边 在完全失去之前\n[03:44.99]你说把爱渐渐放下会走更远\n[03:50.67]\n[03:51.73]或许命运的签 只让我们遇见\n[03:57.60]\n[03:58.47]只让我们相恋这一季的秋天\n[04:04.21]\n[04:05.03]飘落后才发现 这幸福的碎片\n[04:10.64]\n[04:11.69]要我怎么捡",
        "url": "http://dl.stream.qqmusic.qq.com/M500002MXZNu1GToOk.mp3?vkey=91A7F31B4E2F4E9AC6BBB22AE56E1A9C85FC4C7751F51C08569E1245B0EF1015060483610A275B8539C71C0B892D30F678F5E0E404186369&guid=5150825362&fromtag=1",
        "pic": "http://y.gtimg.cn/music/photo_new/T002R300x300M000001UP7mW458ipG.jpg"
    },
    {
        "type": "qq",
        "link": "http://y.qq.com/n/yqq/song/003KtYhg4frNXC.html",
        "songid": "003KtYhg4frNXC",
        "title": "枫",
        "author": "周杰伦",
        "lrc": "[ti:枫]\n[ar:周杰伦 (Jay Chou)]\n[al:十一月的萧邦]\n[by:]\n[offset:0]\n[00:00.00]枫 (Maples) - 周杰伦 (Jay Chou)\n[00:06.32]词：宋健彰\n[00:12.64]曲：周杰伦\n[00:18.96]乌云在我们心里搁下一块阴影\n[00:24.55]\n[00:26.02]我聆听沉寂已久的心情\n[00:31.29]\n[00:31.95]清晰透明就像美丽的风景\n[00:38.96]\n[00:39.79]总在回忆里才看的清\n[00:44.40]\n[00:47.15]被伤透的心能不能够继续爱我\n[00:53.01]\n[00:54.23]我用力牵起没温度的双手\n[00:59.78]\n[01:00.75]过往温柔已经被时间上锁\n[01:08.07]只剩挥散不去的难过\n[01:14.22]\n[01:15.60]缓缓飘落的枫叶像思念\n[01:20.91]我点燃烛火温暖岁末的秋天\n[01:27.09]\n[01:28.02]极光掠夺天边\n[01:31.54]北风掠过想你的容颜\n[01:35.48]\n[01:35.98]我把爱烧成了落叶\n[01:39.58]却换不回熟悉的那张脸\n[01:44.06]缓缓飘落的枫叶像思念\n[01:49.42]为何挽回要赶在冬天来之前\n[01:56.24]\n[01:56.84]爱你穿越时间\n[02:00.01]两行来自秋末的眼泪\n[02:04.48]让爱渗透了地面\n[02:08.12]我要的只是你在我身边\n[02:12.92]\n[02:26.84]被伤透的心能不能够继续爱我\n[02:32.92]\n[02:33.83]我用力牵起没温度的双手\n[02:40.16]过往温柔已经被时间上锁\n[02:46.98]\n[02:47.77]只剩挥散不去的难过\n[02:52.92]\n[02:54.77]在山腰间飘逸的红雨随着北风凋零\n[03:04.59]\n[03:05.10]我轻轻摇曳风铃\n[03:09.12]想唤醒被遗弃的爱情\n[03:14.86]\n[03:15.78]雪花已铺满了地\n[03:18.41]\n[03:19.39]深怕窗外枫叶已结成冰\n[03:23.81]缓缓飘落的枫叶像思念\n[03:29.14]我点燃烛火温暖岁末的秋天\n[03:36.21]极光掠夺天边\n[03:39.71]北风掠过想你的容颜\n[03:44.16]我把爱烧成了落叶\n[03:47.89]却换不回熟悉的那张脸\n[03:52.24]缓缓飘落的枫叶像思念\n[03:57.60]为何挽回要赶在冬天来之前\n[04:04.71]爱你穿越时间\n[04:08.22]两行来自秋末的眼泪\n[04:13.33]\n[04:18.64]让爱渗透了地面\n[04:22.19]我要的只是你在我身边",
        "url": "http://dl.stream.qqmusic.qq.com/M500003KtYhg4frNXC.mp3?vkey=91A7F31B4E2F4E9AC6BBB22AE56E1A9C85FC4C7751F51C08569E1245B0EF1015060483610A275B8539C71C0B892D30F678F5E0E404186369&guid=5150825362&fromtag=1",
        "pic": "http://y.gtimg.cn/music/photo_new/T002R300x300M0000024bjiL2aocxT.jpg"
    },
    {
        "type": "qq",
        "link": "http://y.qq.com/n/yqq/song/004bRWFg3fej9y.html",
        "songid": "004bRWFg3fej9y",
        "title": "彩虹",
        "author": "周杰伦",
        "lrc": "[ti:彩虹]\n[ar:]\n[al:263967]\n[by:]\n[offset:0]\n[00:00.00]彩虹 (《命运呼叫转移》电影主题曲) - 周杰伦 (Jay Chou)\n[00:03.33]词：周杰伦\n[00:06.66]曲：周杰伦\n[00:09.99]编曲：林迈可\n[00:13.32]哪里有彩虹告诉我\n[00:18.18]\n[00:19.01]能不能把我的愿望还给我\n[00:24.68]\n[00:25.76]为什么天这么安静\n[00:31.06]\n[00:31.94]所有的云都跑到我这里\n[00:37.06]\n[00:38.95]有没有口罩一个给我\n[00:43.99]\n[00:44.69]释怀说了太多就成真不了\n[00:51.19]\n[00:51.69]也许时间是一种解药\n[00:57.45]也是我现在正服下的毒药\n[01:04.01]看不见你的笑 我怎么睡得着\n[01:09.87]\n[01:10.39]你的声音这么近我却抱不到\n[01:16.00]\n[01:16.82]没有地球太阳还是会绕\n[01:23.38]没有理由我也能自己走\n[01:29.95]你要离开 我知道很简单\n[01:35.75]\n[01:36.32]你说依赖 是我们的阻碍\n[01:43.01]就算放开 但能不能别没收我的爱\n[01:50.01]当作我最后才明白\n[01:55.12]\n[01:56.76]有没有口罩一个给我\n[02:01.87]\n[02:02.39]释怀说了太多就成真不了\n[02:08.64]\n[02:09.53]也许时间是一种解药\n[02:15.28]也是我现在正服下的毒药\n[02:21.84]看不见你的笑 我怎么睡得着\n[02:27.45]\n[02:28.28]你的声音这么近我却抱不到\n[02:33.64]\n[02:34.90]没有地球太阳还是会绕\n[02:40.51]\n[02:41.03]没有理由我也能自己走\n[02:47.78]你要离开 我知道很简单\n[02:53.33]\n[02:54.22]你说依赖 是我们的阻碍\n[02:59.64]\n[03:00.90]就算放开 但能不能别没收我的爱\n[03:08.03]当作我最后才明白\n[03:13.14]\n[03:14.53]看不见你的笑\n[03:16.28]要我怎么睡得着\n[03:18.22]你的声音这么近我却抱不到\n[03:21.27]没有地球太阳还是会绕会绕\n[03:23.84]没有理由我也能自己走掉\n[03:27.84]释怀说了太多就成真不了\n[03:30.90]也许时间是一种解药解药\n[03:34.47]也是我现在正服下的毒药\n[03:38.64]\n[03:39.72]你要离开 我知道很简单\n[03:45.07]\n[03:46.09]你说依赖 是我们的阻碍\n[03:51.89]\n[03:52.65]就算放开 但能不能别没收我的爱\n[03:59.14]\n[04:03.27]当作我最后才明白",
        "url": "http://dl.stream.qqmusic.qq.com/M500004bRWFg3fej9y.mp3?vkey=91A7F31B4E2F4E9AC6BBB22AE56E1A9C85FC4C7751F51C08569E1245B0EF1015060483610A275B8539C71C0B892D30F678F5E0E404186369&guid=5150825362&fromtag=1",
        "pic": "http://y.gtimg.cn/music/photo_new/T002R300x300M000002eFUFm2XYZ7z.jpg"
    },
    {
        "type": "qq",
        "link": "http://y.qq.com/n/yqq/song/002hXDfk0LX9KO.html",
        "songid": "002hXDfk0LX9KO",
        "title": "听妈妈的话",
        "author": "周杰伦",
        "lrc": "[ti:听妈妈的话]\n[ar:周杰伦]\n[al:依然范特西]\n[by:]\n[offset:0]\n[00:00.00]听妈妈的话 - 周杰伦 (Jay Chou)\n[00:02.52]词：周杰伦\n[00:05.04]曲：周杰伦\n[00:07.56]编曲：林迈可/洪敬尧\n[00:10.08]小朋友 你是否有很多问号\n[00:12.64]为什么 别人在那看漫画\n[00:15.05]我却在学画画 对着钢琴说话\n[00:17.85]别人在玩游戏\n[00:18.86]我却靠在墙壁背我的 ABC\n[00:20.89]我说我要一台大大的飞机\n[00:23.41]但却得到一台旧旧录音机\n[00:26.04]为什么要听妈妈的话\n[00:28.30]长大后你就会开始懂了这段话\n[00:30.91]哼\n[00:31.49]长大后我开始明白\n[00:33.62]为什么我 跑得比别人快\n[00:35.38]飞得比别人高\n[00:36.31]将来大家看的都是我画的漫画\n[00:38.79]大家唱的都是 我写的歌\n[00:41.64]妈妈的辛苦 不让你看见\n[00:44.14]温暖的食谱在她心里面\n[00:46.70]有空就得多握握她的手\n[00:49.26]把手牵着一起梦游\n[00:51.80]听妈妈的话 别让她受伤\n[01:00.76]\n[01:02.06]想快快长大 才能保护她\n[01:11.02]\n[01:12.38]美丽的白发 幸福中发芽\n[01:21.46]\n[01:22.69]天使的魔法 温暖中慈祥\n[01:31.70]\n[01:32.48]在你的未来\n[01:33.52]音乐是你的王牌\n[01:34.71]拿王牌谈个恋爱\n[01:35.91]唉 我不想把你教坏\n[01:37.47]还是听妈妈的话吧\n[01:39.16]晚点再恋爱吧\n[01:40.52]我知道你未来的路\n[01:41.92]但妈比我更清楚\n[01:43.41]你会开始学其他同学\n[01:44.79]在书包写东写西\n[01:45.82]但我建议最好写妈妈\n[01:47.45]我会用功读书\n[01:48.61]用功读书\n[01:49.30]怎么会从我嘴巴说出\n[01:51.08]不想你输\n[01:51.94]所以要叫你用功读书\n[01:53.43]妈妈织给你的毛衣\n[01:54.66]你要好好的收着\n[01:55.85]因为母亲节到的时候\n[01:57.18]我要告诉她我还留着\n[01:58.56]对了 我会遇到了周润发\n[02:00.53]所以你可以跟同学炫耀\n[02:02.21]赌神未来是你爸爸\n[02:03.67]我找不到 童年写的情书\n[02:05.41]你写完不要送人\n[02:06.62]因为过两天你会在操场上捡到\n[02:09.13]你会开始喜欢上流行歌\n[02:11.41]因为张学友开始准备唱吻别\n[02:14.34]听妈妈的话 别让她受伤\n[02:23.04]\n[02:24.45]想快快长大 才能保护她\n[02:33.63]\n[02:34.76]美丽的白发 幸福中发芽\n[02:43.69]\n[02:45.03]天使的魔法 温暖中慈祥\n[02:54.19]\n[02:55.44]听妈妈的话 别让她受伤\n[03:04.58]\n[03:05.77]想快快长大 才能保护她\n[03:14.63]\n[03:16.65]长大后我开始明白\n[03:18.56]为什么我 跑得比别人快\n[03:20.36]飞得比别人高\n[03:21.40]将来大家看的都是我画的漫画\n[03:23.84]大家唱的都是 我写的歌\n[03:26.70]妈妈的辛苦 不让你看见\n[03:28.98]温暖的食谱在她心里面\n[03:31.78]有空就得多握握她的手\n[03:34.33]把手牵着一起梦游\n[03:36.88]听妈妈的话 别让她受伤\n[03:45.55]\n[03:46.77]想快快长大 才能保护她\n[03:55.62]\n[03:57.09]美丽的白发 幸福中发芽\n[04:06.48]\n[04:07.61]天使的魔法 温暖中慈祥",
        "url": "http://dl.stream.qqmusic.qq.com/M500002hXDfk0LX9KO.mp3?vkey=91A7F31B4E2F4E9AC6BBB22AE56E1A9C85FC4C7751F51C08569E1245B0EF1015060483610A275B8539C71C0B892D30F678F5E0E404186369&guid=5150825362&fromtag=1",
        "pic": "http://y.gtimg.cn/music/photo_new/T002R300x300M000002jLGWe16Tf1H.jpg"
    },
    {
        "type": "qq",
        "link": "http://y.qq.com/n/yqq/song/001zMQr71F1Qo8.html",
        "songid": "001zMQr71F1Qo8",
        "title": "夜曲",
        "author": "周杰伦",
        "lrc": "[ti:夜曲]\n[ar:周杰伦]\n[al:十一月的萧邦]\n[by:]\n[offset:0]\n[00:00.00]夜曲 - 周杰伦 (Jay Chou)\n[00:06.29]词：方文山\n[00:12.58]曲：周杰伦\n[00:18.87]编曲：林迈可\n[00:25.17]一群嗜血的蚂蚁 被腐肉所吸引\n[00:28.02]我面无表情 看孤独的风景\n[00:30.93]失去你 爱恨开始分明\n[00:33.65]失去你 还有什么事好关心\n[00:36.58]当鸽子不再象征和平\n[00:38.54]我终于被提醒\n[00:39.78]广场上喂食的是秃鹰\n[00:41.83]我用漂亮的押韵\n[00:43.34]形容被掠夺一空的爱情\n[00:45.29]\n[00:47.28]啊 乌云开始遮蔽 夜色不干净\n[00:49.72]公园里 葬礼的回音 在漫天飞行\n[00:52.58]送你的白色玫瑰\n[00:54.01]在纯黑的环境凋零\n[00:55.69]乌鸦在树枝上诡异的很安静\n[00:57.98]静静听 我黑色的大衣\n[01:00.41]想温暖你日渐冰冷的回忆\n[01:02.40]走过的 走过的 生命\n[01:03.68]啊 四周弥漫雾气\n[01:05.51]我在空旷的墓地\n[01:06.74]老去后还爱你\n[01:07.78]\n[01:09.45]为你弹奏肖邦的夜曲\n[01:11.49]\n[01:12.12]纪念我死去的爱情\n[01:14.23]\n[01:14.84]跟夜风一样的声音\n[01:17.74]心碎的很好听\n[01:19.84]\n[01:20.39]手在键盘敲很轻\n[01:22.50]\n[01:23.17]我给的思念很小心\n[01:25.28]\n[01:25.91]你埋葬的地方叫幽冥\n[01:29.39]\n[01:30.49]为你弹奏肖邦的夜曲\n[01:33.58]\n[01:34.17]纪念我死去的爱情\n[01:36.30]\n[01:36.96]而我为你隐姓埋名\n[01:39.76]在月光下弹琴\n[01:41.94]\n[01:42.49]对你心跳的感应\n[01:44.52]\n[01:45.19]还是如此温热亲近\n[01:47.35]\n[01:47.94]怀念你那鲜红的唇印\n[01:51.41]\n[02:15.63]那些断翅的蜻蜓 散落在这森林\n[02:18.29]而我的眼睛 没有丝毫同情\n[02:20.83]\n[02:21.55]失去你 泪水混浊不清\n[02:23.90]失去你 我连笑容都有阴影\n[02:26.28]\n[02:26.84]风在长满青苔的屋顶\n[02:28.80]嘲笑我的伤心\n[02:30.06]像一口没有水的枯井\n[02:32.16]我用凄美的字型\n[02:33.59]描绘后悔莫及的那爱情\n[02:35.42]\n[02:37.64]为你弹奏肖邦的夜曲\n[02:39.67]\n[02:40.36]纪念我死去的爱情\n[02:42.51]\n[02:43.18]跟夜风一样的声音\n[02:45.88]心碎的很好听\n[02:48.10]\n[02:48.69]手在键盘敲很轻\n[02:50.74]\n[02:51.42]我给的思念很小心\n[02:53.54]\n[02:54.13]你埋葬的地方叫幽冥\n[02:57.69]\n[02:58.74]为你弹奏肖邦的夜曲\n[03:01.79]\n[03:02.49]纪念我死去的爱情\n[03:04.53]\n[03:05.23]而我为你隐姓埋名\n[03:07.97]在月光下弹琴\n[03:10.08]\n[03:10.72]对你心跳的感应\n[03:12.83]\n[03:13.45]还是如此温热亲近\n[03:15.58]\n[03:16.24]怀念你那鲜红的唇印\n[03:19.20]\n[03:21.81]一群嗜血的蚂蚁 被腐肉所吸引\n[03:24.45]我面无表情 看孤独的风景\n[03:27.50]失去你 爱恨开始分明\n[03:29.55]\n[03:30.17]失去你 还有什么事好关心\n[03:32.94]当鸽子不再象征和平\n[03:34.93]我终于被提醒\n[03:36.01]\n[03:36.52]广场上喂食的是秃鹰\n[03:38.52]我用漂亮的押韵\n[03:39.69]形容被掠夺一空的爱情",
        "url": "http://dl.stream.qqmusic.qq.com/M500001zMQr71F1Qo8.mp3?vkey=91A7F31B4E2F4E9AC6BBB22AE56E1A9C85FC4C7751F51C08569E1245B0EF1015060483610A275B8539C71C0B892D30F678F5E0E404186369&guid=5150825362&fromtag=1",
        "pic": "http://y.gtimg.cn/music/photo_new/T002R300x300M0000024bjiL2aocxT.jpg"
    },
    {
        "type": "qq",
        "link": "http://y.qq.com/n/yqq/song/003cI52o4daJJL.html",
        "songid": "003cI52o4daJJL",
        "title": "花海",
        "author": "周杰伦",
        "lrc": "[ti:花海]\n[ar:周杰伦]\n[al:魔杰座]\n[by:]\n[offset:0]\n[00:00.00]花海 - 周杰伦 (Jay Chou)\n[00:06.69]词：古小力/黄凌嘉\n[00:13.38]曲：周杰伦\n[00:20.07]编曲：黄雨勋\n[00:26.77]静止了 所有的花开\n[00:32.23]\n[00:33.16]遥远了 清晰了爱\n[00:38.46]\n[00:39.46]天郁闷 爱却很喜欢\n[00:45.20]\n[00:45.89]那时候我不懂这叫爱\n[00:51.42]\n[00:52.35]你喜欢 站在那窗台\n[00:58.56]你好久 都没再来\n[01:04.18]\n[01:05.10]彩色的时间染上空白\n[01:11.39]\n[01:12.15]是你流的泪晕开\n[01:17.03]不要你离开\n[01:20.27]距离隔不开\n[01:23.45]思念变成海\n[01:26.46]在窗外进不来\n[01:29.80]原谅说太快\n[01:33.03]爱成了阻碍\n[01:36.20]手中的风筝放太快回不来\n[01:42.63]不要你离开\n[01:45.84]回忆划不开\n[01:49.03]欠你的宠爱\n[01:51.76]我在等待重来\n[01:54.85]\n[01:55.43]天空仍灿烂\n[01:58.65]它爱着大海\n[02:01.86]情歌被打败\n[02:05.02]爱已不存在\n[02:10.21]\n[02:34.72]你喜欢 站在那窗台\n[02:40.13]\n[02:40.97]你好久 都没再来\n[02:46.25]\n[02:47.43]彩色的时间染上空白\n[02:53.78]\n[02:54.65]是你流的泪晕开\n[02:58.82]\n[02:59.51]不要你离开\n[03:02.63]距离隔不开\n[03:05.84]思念变成海\n[03:08.69]在窗外进不来\n[03:12.21]原谅说太快\n[03:15.39]爱成了阻碍\n[03:18.64]手中的风筝放太快回不来\n[03:25.11]不要你离开\n[03:28.25]回忆划不开\n[03:31.42]欠你的宠爱\n[03:34.34]我在等待重来\n[03:37.81]天空仍灿烂\n[03:41.07]它爱着大海\n[03:44.23]情歌被打败\n[03:46.93]\n[03:47.45]爱已不存在",
        "url": "http://dl.stream.qqmusic.qq.com/M500003cI52o4daJJL.mp3?vkey=91A7F31B4E2F4E9AC6BBB22AE56E1A9C85FC4C7751F51C08569E1245B0EF1015060483610A275B8539C71C0B892D30F678F5E0E404186369&guid=5150825362&fromtag=1",
        "pic": "http://y.gtimg.cn/music/photo_new/T002R300x300M000002Neh8l0uciQZ.jpg"
    },
    {
        "type": "qq",
        "link": "http://y.qq.com/n/yqq/song/000xdZuV2LcQ19.html",
        "songid": "000xdZuV2LcQ19",
        "title": "甜甜的",
        "author": "周杰伦",
        "lrc": "[ti:甜甜的]\n[ar:周杰伦]\n[al:我很忙]\n[by:]\n[offset:0]\n[00:00.00]甜甜的 - 周杰伦 (Jay Chou)\n[00:00.35]词：方文山\n[00:00.71]曲：周杰伦\n[00:01.06]编曲：林迈可\n[00:01.42]制作人：周杰伦\n[00:01.77]我轻轻地尝一口\n[00:03.81]你说的爱我\n[00:05.65]还在回味你给过的温柔\n[00:08.62]\n[00:09.91]我轻轻地尝一口\n[00:12.11]这香浓的诱惑\n[00:13.92]我喜欢的样子你都有\n[00:17.03]\n[00:24.78]你爱过头 竟然答应我\n[00:27.69]\n[00:28.26]要给我蜂蜜口味的生活\n[00:31.89]\n[00:32.62]加一颗奶球 我搅拌害羞\n[00:36.44]将甜度调高后再牵手\n[00:40.20]\n[00:41.08]你的爱太多 想随身带走\n[00:44.24]\n[00:44.80]想你的时候 就吃上一口\n[00:48.59]\n[00:49.41]我温热着 被呵护的感受\n[00:52.96]却又担心降温了要求\n[00:56.15]\n[00:57.47]我尝着你话里面的奶油溜啊溜\n[01:01.16]\n[01:01.74]听过的每句话都很可口呦啊呦\n[01:05.30]\n[01:05.99]那些多余的画面全被跳过\n[01:09.94]\n[01:10.66]你的眼中只有我\n[01:13.43]\n[01:14.16]Oh oh\n[01:14.87]\n[01:16.17]我轻轻地尝一口你说的爱我\n[01:20.08]还在回味你给过的温柔\n[01:23.68]\n[01:24.29]我轻轻地尝一口 这香浓的诱惑\n[01:28.33]我喜欢的样子你都有\n[01:31.80]\n[01:32.66]我轻轻地尝一口你说的爱我\n[01:36.67]舍不得吃会微笑的糖果\n[01:40.86]我轻轻地尝一口 份量虽然不多\n[01:44.98]却将你的爱完全吸收\n[01:48.37]\n[02:08.28]我微笑着 让香味停留\n[02:11.12]\n[02:11.64]缘分走到这也赖着不走\n[02:16.09]像夹心饼干 中间有甜头\n[02:19.41]\n[02:19.92]继续下去不需要理由\n[02:23.41]\n[02:24.62]我尝着你话里面的奶油溜啊溜\n[02:27.98]\n[02:28.71]听过的每句话都很可口呦啊呦\n[02:32.10]\n[02:32.83]那些多余的画面全被跳过\n[02:36.72]\n[02:37.48]你的眼中只有我\n[02:41.06]\n[02:42.98]我轻轻地尝一口 你说的爱我\n[02:47.01]还在回味你给过的温柔\n[02:50.56]\n[02:51.14]我轻轻地尝一口这香浓的诱惑\n[02:55.36]我喜欢的样子你都有\n[02:58.99]\n[02:59.57]我轻轻地尝一口 你说的爱我\n[03:03.56]舍不得吃会微笑的糖果\n[03:07.22]\n[03:07.81]我轻轻地尝一口 份量虽然不多\n[03:11.94]却将你的爱完全吸收\n[03:15.22]\n[03:16.38]我轻轻地尝一口 你说的爱我\n[03:20.19]还在回味你给过的温柔\n[03:23.37]\n[03:24.46]我轻轻地尝一口味道香浓的说\n[03:28.44]我喜欢的样子你都有\n[03:31.83]\n[03:32.71]我轻轻地尝一口 你说的爱我\n[03:36.77]舍不得吃会微笑的糖果\n[03:40.26]\n[03:41.00]我轻轻地尝一口 份量虽然不多\n[03:45.03]却将你的爱完全吸收",
        "url": "http://dl.stream.qqmusic.qq.com/M500000xdZuV2LcQ19.mp3?vkey=91A7F31B4E2F4E9AC6BBB22AE56E1A9C85FC4C7751F51C08569E1245B0EF1015060483610A275B8539C71C0B892D30F678F5E0E404186369&guid=5150825362&fromtag=1",
        "pic": "http://y.gtimg.cn/music/photo_new/T002R300x300M000002eFUFm2XYZ7z.jpg"
    },
    {
        "type": "qq",
        "link": "http://y.qq.com/n/yqq/song/003rxgIM2eOFSF.html",
        "songid": "003rxgIM2eOFSF",
        "title": "回到过去",
        "author": "周杰伦",
        "lrc": "[ti:回到过去]\n[ar:周杰伦]\n[al:八度空间]\n[by:]\n[offset:0]\n[00:00.00]回到过去 - 周杰伦 (Jay Chou)\n[00:01.93]词：刘畊宏\n[00:03.86]曲：周杰伦\n[00:05.79]编曲：林迈可\n[00:07.72]一盏黄黄旧旧的灯\n[00:11.72]\n[00:13.22]时间在旁闷不吭声\n[00:17.37]\n[00:18.81]寂寞下手毫无分寸\n[00:23.16]\n[00:24.41]不懂得轻重之分\n[00:28.14]\n[00:30.11]沉默支撑跃过陌生\n[00:34.47]\n[00:35.92]静静看着凌晨黄昏\n[00:40.12]\n[00:41.56]你的身影\n[00:42.81]\n[00:44.35]失去平衡\n[00:46.03]慢慢下沉\n[00:48.57]\n[00:52.09]黑暗已在空中盘旋\n[00:56.02]该往哪我看不见\n[00:59.90]\n[01:01.20]也许爱在梦的另一端\n[01:05.56]\n[01:06.67]无法存活在真实的空间\n[01:11.25]\n[01:12.31]想回到过去\n[01:13.97]\n[01:15.47]试着抱你在怀里\n[01:18.31]\n[01:18.97]羞怯的脸带有一点稚气\n[01:22.43]\n[01:24.22]想看你看的世界\n[01:26.61]\n[01:27.14]想在你梦的画面\n[01:29.87]只要靠在一起\n[01:32.16]就能感觉甜蜜\n[01:33.89]\n[01:35.04]想回到过去\n[01:36.53]\n[01:37.99]试着让故事继续\n[01:40.75]\n[01:41.54]至少不再让你离我而去\n[01:45.14]\n[01:46.82]分散时间的注意\n[01:49.57]这次会抱得更紧\n[01:51.88]\n[01:52.47]这样挽留不知\n[01:54.53]还来不来得及\n[01:56.20]\n[01:57.17]想回到过去\n[01:59.04]\n[02:05.22]思绪不断\n[02:06.66]阻挡着回忆播放\n[02:09.40]盲目的追寻\n[02:11.24]仍然空空荡荡\n[02:13.12]\n[02:15.09]灰蒙蒙的夜晚\n[02:17.20]睡意又不知躲到哪去\n[02:20.22]\n[02:21.09]一转身孤单\n[02:22.85]已躺在身旁\n[02:24.54]\n[02:28.51]想回到过去\n[02:30.14]\n[02:31.68]试着抱你在怀里\n[02:34.30]\n[02:35.17]羞怯的脸带有一点稚气\n[02:38.52]\n[02:40.47]想看你看的世界\n[02:43.20]想在你梦的画面\n[02:46.07]只要靠在一起\n[02:48.37]就能感觉甜蜜\n[02:49.93]\n[02:51.09]想回到过去\n[02:52.64]\n[02:54.23]试着让故事继续\n[02:56.80]\n[02:57.79]至少不再让你离我而去\n[03:01.15]\n[03:03.03]分散时间的注意\n[03:05.82]这次会抱得更紧\n[03:08.73]这样挽留不知\n[03:10.81]还来不来得及\n[03:12.59]\n[03:13.40]想回到过去\n[03:15.33]\n[03:22.48]沉默支撑跃过陌生\n[03:26.44]\n[03:28.11]静静看着凌晨黄昏\n[03:32.30]\n[03:33.76]你的身影\n[03:34.93]\n[03:36.56]失去平衡\n[03:37.92]\n[03:39.39]慢慢下沉\n[03:41.10]\n[03:42.13]想回到过去",
        "url": "http://dl.stream.qqmusic.qq.com/M500003rxgIM2eOFSF.mp3?vkey=91A7F31B4E2F4E9AC6BBB22AE56E1A9C85FC4C7751F51C08569E1245B0EF1015060483610A275B8539C71C0B892D30F678F5E0E404186369&guid=5150825362&fromtag=1",
        "pic": "http://y.gtimg.cn/music/photo_new/T002R300x300M000004MGitN0zEHpb.jpg"
    },
    {
        "type": "qq",
        "link": "http://y.qq.com/n/yqq/song/0031TAKo0095np.html",
        "songid": "0031TAKo0095np",
        "title": "不爱我就拉倒",
        "author": "周杰伦",
        "lrc": "[ti:不爱我就拉倒]\n[ar:周杰伦]\n[al:不爱我就拉倒]\n[by:]\n[offset:0]\n[00:00.00]不爱我就拉倒 (If You Don’t Love Me, It’s Fine) - 周杰伦 (Jay Chou)\n[00:03.70]词：周杰伦/宋健彰（弹头）\n[00:07.40]曲：周杰伦\n[00:11.11]寒流来了 刚好\n[00:14.39]\n[00:15.41]刚好可以 把你手放外套\n[00:20.10]\n[00:22.17]把安全帽戴好\n[00:25.52]\n[00:26.72]不让你在 爱情路上跌倒\n[00:31.35]\n[00:32.15]加速狂飙 你说不要\n[00:36.77]\n[00:37.71]爱的险你不想冒\n[00:41.63]不想被套牢\n[00:45.27]\n[00:46.11]他的怀抱 真比我好\n[00:50.77]\n[00:51.28]你幸福就好\n[00:54.29]不爱我就拉倒\n[00:57.22]离开之前\n[00:59.88]不要爱的抱抱\n[01:02.83]反正 我又不是没有人要\n[01:08.08]哥练的胸肌\n[01:10.09]如果你还想靠\n[01:13.92]\n[01:16.87]好胆你就麦造\n[01:18.74]寒流来了 刚好可以把你手放外套\n[01:21.28]把安全帽戴好\n[01:22.29]不要在爱情路上跌倒\n[01:24.09]加速狂飙 你 你说不要\n[01:26.43]爱的险你不想冒\n[01:27.77]不想被我给套牢\n[01:29.58]反正我又不是没有人要\n[01:32.27]哥练的胸肌如果你还想靠\n[01:35.24]算了 你幸福你幸福就好\n[01:38.29]\n[01:40.70]寒流来了 刚好\n[01:43.63]\n[01:44.86]刚好可以 把你手放外套\n[01:49.07]\n[01:51.64]把安全帽戴好\n[01:54.98]\n[01:55.76]不让你在 爱情路上跌倒\n[02:00.73]\n[02:01.50]加速狂飙 你说不要\n[02:06.16]\n[02:07.03]爱的险你不想冒\n[02:10.85]不想被套牢\n[02:15.39]他的怀抱 真比我好\n[02:20.74]你幸福就好\n[02:23.01]\n[02:23.70]不爱我就拉倒\n[02:26.60]离开之前\n[02:28.69]\n[02:29.22]不要爱的抱抱\n[02:31.35]\n[02:32.22]反正 我又不是没有人要\n[02:37.42]哥练的胸肌\n[02:39.54]如果你还想靠\n[02:44.39]\n[02:46.07]好胆你就麦造\n[02:48.23]\n[03:05.22]你幸福就好\n[03:08.31]\n[03:10.97]不爱我就拉倒\n[03:13.24]\n[03:14.07]离开之前\n[03:16.15]\n[03:16.65]不要爱的抱抱\n[03:19.67]反正 我又不是没有人要\n[03:24.91]哥练的胸肌\n[03:26.90]如果你还想靠\n[03:30.01]\n[03:33.37]好胆你就麦造",
        "url": "http://dl.stream.qqmusic.qq.com/M5000031TAKo0095np.mp3?vkey=91A7F31B4E2F4E9AC6BBB22AE56E1A9C85FC4C7751F51C08569E1245B0EF1015060483610A275B8539C71C0B892D30F678F5E0E404186369&guid=5150825362&fromtag=1",
        "pic": "http://y.gtimg.cn/music/photo_new/T002R300x300M000001CnPE31iJ899.jpg"
    },
    {
        "type": "qq",
        "link": "http://y.qq.com/n/yqq/song/000sxzol11raSd.html",
        "songid": "000sxzol11raSd",
        "title": "不该 (with aMEI)",
        "author": "周杰伦",
        "lrc": "[ti:不该 (with aMEI)]\n[ar:周杰伦]\n[al:]\n[by:]\n[offset:0]\n[00:00.88]不该 (with aMEI) (Shouldn't Be) (《幻城》电视剧片头曲|《幻城凡世》网络剧片尾曲) - 周杰伦 (Jay Chou)\n[00:05.54]\n[00:06.12]词：方文山\n[00:08.62]曲：周杰伦\n[00:10.29]\n[00:24.31]Jay：\n[00:25.91]\n[00:26.67]假装我们还在一块\n[00:30.83]\n[00:33.16]我真的演不出来\n[00:36.31]\n[00:39.46]还是不习惯你不在\n[00:43.97]\n[00:44.89]这身份转变太快\n[00:48.43]\n[00:49.64]aMEI：\n[00:50.73]\n[00:51.89]画面里不需要旁白\n[00:57.12]\n[00:58.64]却谁都看的出来\n[01:02.74]\n[01:05.02]是我情绪涌了上来\n[01:09.97]\n[01:10.64]想哭却一遍空白\n[01:14.29]\n[01:15.52]Jay：\n[01:16.90]雪地里相爱\n[01:18.13]他们说零下已结晶的誓言不会坏\n[01:22.47]合：\n[01:23.25]但爱的状态\n[01:24.53]却不会永远都冰封\n[01:26.93]而透明的存在\n[01:28.84]合：\n[01:29.20]轻轻飘 落下来\n[01:32.19]许下的梦 融化的太快\n[01:35.05]\n[01:36.01]或许我们都不该醒来\n[01:39.79]\n[01:40.71]aMEI：\n[01:41.46]你还是住在我的回忆里不出来\n[01:47.55]Jay：\n[01:48.07]让我们微笑离开让故事留下来\n[01:53.75]合：\n[01:54.26]放手后爱依然在\n[01:57.41]雪融了就应该花开\n[02:01.86]缘若尽了\n[02:03.47]就不该再重来\n[02:06.64]aMEI：\n[02:07.19]你依旧住在我的回忆里不出来\n[02:13.07]Jay：\n[02:13.52]我离开将你的手交给下个最爱\n[02:19.25]aMEI：\n[02:19.85]纠缠与\n[02:20.80]合：\n[02:21.14]Oh 固执等待\n[02:23.00]反而是另一种伤害\n[02:26.83]\n[02:27.34]彼此紧握的手松开\n[02:30.88]去拥抱更多未来\n[02:34.69]\n[02:45.95]Jay：\n[02:47.15]错过的时间怎么买\n[02:51.57]\n[02:53.91]谁都付不出来\n[02:57.30]\n[02:57.86]aMEI：\n[02:59.34]\n[03:00.18]或许我们学会释怀\n[03:04.37]\n[03:05.71]让过去安静下来\n[03:09.13]\n[03:11.07]合：\n[03:12.24]雪地里相爱\n[03:13.34]他们说零下已结晶的誓言不会坏\n[03:17.44]\n[03:18.53]但爱的状态\n[03:19.79]却不会永远都冰封\n[03:22.12]而透明的存在\n[03:23.91]合：\n[03:24.43]轻轻飘 落下来\n[03:27.45]许下的梦融化的太快\n[03:30.31]\n[03:31.09]或许我们都不该醒来\n[03:34.79]\n[03:36.28]aMEI：\n[03:36.80]你还是住在我的回忆里不出来\n[03:42.73]Jay：\n[03:43.22]让我们微笑离开让故事留下来\n[03:49.03]合：\n[03:49.51]放手后爱依然在\n[03:52.57]雪融了就应该花开\n[03:56.32]\n[03:56.98]缘若尽了\n[03:58.57]就不该再重来\n[04:01.83]aMEI：\n[04:02.34]你依旧住在我的回忆里不出来\n[04:08.28]Jay：\n[04:08.73]我离开将你的手交给下个\n[04:12.67]合：\n[04:13.16]最爱\n[04:15.09]aMEI：\n[04:15.54]纠缠与\n[04:16.10]合：\n[04:16.45]Oh固执等待\n[04:18.27]反而是另一种伤害\n[04:22.67]彼此紧握的手松开\n[04:26.21]去拥抱更多未来",
        "url": "http://dl.stream.qqmusic.qq.com/M500000sxzol11raSd.mp3?vkey=91A7F31B4E2F4E9AC6BBB22AE56E1A9C85FC4C7751F51C08569E1245B0EF1015060483610A275B8539C71C0B892D30F678F5E0E404186369&guid=5150825362&fromtag=1",
        "pic": "http://y.gtimg.cn/music/photo_new/T002R300x300M000003RMaRI1iFoYd.jpg"
    },
    {
        "type": "qq",
        "link": "http://y.qq.com/n/yqq/song/0036g6g628i2gI.html",
        "songid": "0036g6g628i2gI",
        "title": "轨迹",
        "author": "周杰伦",
        "lrc": "[ti:轨迹]\n[ar:周杰伦]\n[al:寻找周杰伦EP]\n[by:]\n[offset:0]\n[00:00.00]轨迹 (Footprints) (《寻找周杰伦》电影主题曲) - 周杰伦 (Jay Chou)\n[00:03.90]词：黄俊郎\n[00:07.80]曲：周杰伦\n[00:11.70]编曲：钟兴民\n[00:15.61]制作人：周杰伦\n[00:19.51]怎么隐藏我的悲伤失去你的地方\n[00:32.08]你的发香散的匆忙我已经跟不上\n[00:44.08]\n[00:44.95]闭上眼睛还能看见你离去的痕迹\n[00:56.83]\n[00:57.58]在月光下一直找寻那想念的身影\n[01:09.52]\n[01:10.83]如果说分手是苦痛的起点\n[01:16.34]那在终点之前我愿意再爱一遍\n[01:23.46]想要对你说的不敢说的爱\n[01:29.51]会不会有人可以明白\n[01:35.74]我会发着呆然后忘记你\n[01:42.19]接着紧紧闭上眼\n[01:48.56]想着那一天会有人代替\n[01:55.43]让我不再想念你\n[02:00.81]\n[02:01.38]我会发着呆然后微微笑\n[02:07.79]接着紧紧闭上眼\n[02:14.36]又想了一遍你温柔的脸\n[02:20.98]在我忘记之前\n[02:26.42]\n[02:41.68]闭上眼睛还能看见你离去的痕迹\n[02:53.25]\n[02:54.15]在月光下一直找寻那想念的身影\n[03:06.79]\n[03:07.41]如果说分手是苦痛的起点\n[03:12.78]那在终点之前我愿意再爱一遍\n[03:20.03]想要对你说的不敢说的爱\n[03:25.98]会不会有人可以明白\n[03:32.31]我会发着呆然后忘记你\n[03:38.75]接着紧紧闭上眼\n[03:45.12]想着那一天会有人代替\n[03:51.94]让我不再想念你\n[03:57.13]\n[04:01.95]我会发着呆然后忘记你\n[04:08.42]接着紧紧闭上眼\n[04:15.31]想着那一天会有人代替\n[04:22.18]让我不再想念你\n[04:28.20]我会发着呆然后微微笑\n[04:34.53]接着紧紧闭上眼\n[04:40.84]又想了一遍你温柔的脸\n[04:47.08]\n[04:47.78]在我忘记之前心里的眼泪\n[04:56.97]模糊了视线你已快看不见",
        "url": "http://dl.stream.qqmusic.qq.com/M5000036g6g628i2gI.mp3?vkey=AEE74D5DAB8C851E531D4A44DD6AE7CA2047C72D953BFFC60A8CE3D6C858655BFE30013A98BA4F9AA6681B5FDC1C863CFF14847A64503D66&guid=5150825362&fromtag=1",
        "pic": "http://y.gtimg.cn/music/photo_new/T002R300x300M000001BGzMs369FzU.jpg"
    },
    {
        "type": "qq",
        "link": "http://y.qq.com/n/yqq/song/003ZdxP61ClQZ5.html",
        "songid": "003ZdxP61ClQZ5",
        "title": "断了的弦",
        "author": "周杰伦",
        "lrc": "[ti:断了的弦]\n[ar:周杰伦]\n[al:寻找周杰伦]\n[by:]\n[offset:0]\n[00:00.00]断了的弦 (《寻找周杰伦》电影插曲) - 周杰伦 (Jay Chou)\n[00:04.65]词：方文山\n[00:09.31]曲：周杰伦\n[00:13.96]编曲：钟兴民\n[00:18.62]断了的弦 再怎么练\n[00:23.51]我的感觉你已听不见\n[00:28.46]你的转变像断掉的弦\n[00:33.37]再怎么接 音都不对\n[00:36.75]你的改变我能够分辨\n[00:40.50]我沉默 你的话也不多\n[00:43.61]\n[00:44.48]我们之间少了什么不说\n[00:48.48]哎唷\n[00:49.74]微笑后表情终于有点难过\n[00:53.37]握着你的手\n[00:54.49]问你 确定了再走\n[00:57.66]\n[00:59.69]我突然释怀的笑\n[01:02.11]笑声盘旋半山腰\n[01:04.56]随风在飘摇啊摇\n[01:07.06]来到你的面前绕\n[01:09.56]你泪水往下的掉\n[01:12.01]说会记住我的好\n[01:14.46]我也弯起了嘴角笑\n[01:17.55]\n[01:19.44]你的美已经给了谁\n[01:23.79]追了又追我要不回\n[01:29.35]我了解离开树的叶\n[01:33.65]属于地上的世界凋谢\n[01:40.06]断了的弦再弹一遍\n[01:45.11]我的世界你不在里面\n[01:50.04]我的指尖已经弹出茧\n[01:54.94]还是无法留你在我身边\n[01:59.91]断了的弦 再怎么练\n[02:04.90]我的感觉你已听不见\n[02:09.86]你的转变像断掉的弦\n[02:14.70]再怎么接 音都不对\n[02:18.19]你的改变我能够分辨\n[02:21.99]\n[02:31.79]我沉默 你的话也不多\n[02:34.96]\n[02:35.81]我们之间少了什么不说\n[02:39.76]哎唷\n[02:41.02]微笑后表情终于有点难过\n[02:44.73]握着你的手\n[02:45.85]问你 确定了再走\n[02:50.95]我突然释怀的笑\n[02:53.45]笑声盘旋半山腰\n[02:55.93]随风在飘摇啊摇\n[02:58.39]来到你的面前绕\n[03:00.95]你泪水往下的掉\n[03:03.38]说会记住我的好\n[03:05.84]我也弯起了嘴角笑\n[03:10.83]你的美已经给了谁\n[03:15.14]追了又追我要不回\n[03:20.73]我了解离开树的叶\n[03:25.01]属于地上的世界凋谢\n[03:30.71]\n[03:31.44]断了的弦再弹一遍\n[03:36.50]我的世界你不在里面\n[03:41.41]我的指尖已经弹出茧\n[03:46.36]还是无法留你在我身边\n[03:51.27]断了的弦 再怎么练\n[03:56.26]我的感觉你已听不见\n[04:01.19]你的转变像断掉的弦\n[04:06.12]再怎么接 音都不对\n[04:09.56]你的改变我能够分辨",
        "url": "http://dl.stream.qqmusic.qq.com/M500003ZdxP61ClQZ5.mp3?vkey=AEE74D5DAB8C851E531D4A44DD6AE7CA2047C72D953BFFC60A8CE3D6C858655BFE30013A98BA4F9AA6681B5FDC1C863CFF14847A64503D66&guid=5150825362&fromtag=1",
        "pic": "http://y.gtimg.cn/music/photo_new/T002R300x300M000001BGzMs369FzU.jpg"
    },
    {
        "type": "qq",
        "link": "http://y.qq.com/n/yqq/song/002OKIox28ad9a.html",
        "songid": "002OKIox28ad9a",
        "title": "半岛铁盒",
        "author": "周杰伦",
        "lrc": "[ti:半岛铁盒]\n[ar:周杰伦]\n[al:八度空间]\n[by:]\n[offset:0]\n[00:00.00]半岛铁盒 - 周杰伦 (Jay Chou)\n[00:04.28]词：周杰伦\n[00:08.56]曲：周杰伦\n[00:12.84]编曲：林迈可\n[00:17.12]走廊灯关上 书包放\n[00:19.19]走到房间窗外望\n[00:21.17]回想刚买的书\n[00:22.75]一本名叫半岛铁盒\n[00:24.67]放在床边堆好多\n[00:26.38]第一页第六页第七页序\n[00:28.65]我永远都想不到\n[00:30.23]陪我看这书的你会要走\n[00:32.15]不再是不再有\n[00:33.97]现在已经看不到\n[00:36.21]铁盒的钥匙孔\n[00:37.58]透了光看见它锈了好久\n[00:39.74]好旧好旧\n[00:40.90]外围的灰尘包围了我\n[00:43.38]好暗好暗\n[00:44.47]铁盒的钥匙我找不到\n[00:47.33]放在糖果旁的\n[00:49.90]是我很想回忆的甜\n[00:54.64]然而过滤了你和我\n[00:57.88]沦落而成美\n[01:00.83]\n[01:02.17]沉在盒子里的是你\n[01:05.30]给我的快乐\n[01:08.15]\n[01:09.31]我很想记得可是我记不得\n[01:14.56]\n[01:15.11]为什么这样子\n[01:18.60]你拉着我 说你有些犹豫\n[01:22.89]怎么这样子\n[01:25.92]雨还没停你就撑伞要走\n[01:30.05]已经习惯不去阻止你\n[01:33.85]过好一阵子你就会回来\n[01:38.24]印象中的爱情\n[01:40.60]好像顶不住那时间\n[01:44.50]为什么这样子\n[01:47.82]你看着我说你已经决定\n[01:52.22]我拉不住你\n[01:55.20]他的手应该比我更暖\n[01:59.71]铁盒的序变成了日记\n[02:03.40]变成了空气 演化成回忆\n[02:07.59]印象中的爱情\n[02:10.13]好像顶不住那时间\n[02:13.89]所以你弃权\n[02:16.94]\n[02:29.74]走廊灯关上 书包放\n[02:32.05]走到房间窗外望\n[02:33.87]回想刚买的书\n[02:35.58]一本名叫半岛铁盒\n[02:37.56]放在床 边堆好多\n[02:39.33]第一页第六页第七页序\n[02:41.37]我永远都想不到\n[02:43.12]陪我看这书的你会要走\n[02:45.05]不再是不再有\n[02:46.85]现在已经看不到\n[02:48.69]铁盒的钥匙孔 透了光\n[02:50.92]看见它锈了好久\n[02:52.43]好旧好旧\n[02:53.98]外围的灰尘包围了我\n[02:56.12]好暗好暗\n[02:57.25]铁盒的钥匙我找不到\n[03:00.20]放在糖果旁的\n[03:02.61]是我很想回忆的甜\n[03:06.49]\n[03:07.47]然而过滤了你和我\n[03:10.60]沦落而成美\n[03:13.43]\n[03:14.96]沉在盒子里的是你\n[03:18.03]给我的快乐\n[03:20.42]\n[03:22.04]我很想记得可是我记不得\n[03:27.31]\n[03:27.93]为什么这样子\n[03:31.11]你拉着我说你有些犹豫\n[03:35.45]怎么这样子\n[03:38.68]雨还没停你就撑伞要走\n[03:42.84]已经习惯不去阻止你\n[03:46.68]过好一阵子你就会回来\n[03:51.07]印象中的爱情\n[03:53.48]好像顶不住那时间\n[03:57.22]为什么这样子\n[04:00.42]\n[04:00.94]你拉着我 说你有些犹豫\n[04:04.99]怎么这样子\n[04:07.85]\n[04:08.37]雨还没停你就撑伞要走\n[04:12.49]已经习惯不去阻止你\n[04:16.21]过好一阵子你就会回来\n[04:20.19]\n[04:20.76]印象中的爱情\n[04:23.05]好像顶不住那时间\n[04:26.98]为什么这样子\n[04:29.96]\n[04:30.63]你看着我说你已经决定\n[04:34.60]我拉不住你\n[04:37.91]他的手应该比我更暖\n[04:42.39]\n[04:43.14]铁盒的序变成了日记\n[04:45.63]变成了空气 演化成回忆\n[04:50.24]印象中的爱情\n[04:52.93]好像顶不住那时间\n[04:56.96]所以你弃权",
        "url": "http://dl.stream.qqmusic.qq.com/M500002OKIox28ad9a.mp3?vkey=AEE74D5DAB8C851E531D4A44DD6AE7CA2047C72D953BFFC60A8CE3D6C858655BFE30013A98BA4F9AA6681B5FDC1C863CFF14847A64503D66&guid=5150825362&fromtag=1",
        "pic": "http://y.gtimg.cn/music/photo_new/T002R300x300M000004MGitN0zEHpb.jpg"
    },
    {
        "type": "qq",
        "link": "http://y.qq.com/n/yqq/song/003uEbEr0jcW7c.html",
        "songid": "003uEbEr0jcW7c",
        "title": "东风破",
        "author": "周杰伦",
        "lrc": "[ti:东风破]\n[ar:]\n[al:315611]\n[by:]\n[offset:0]\n[00:00.00]东风破 (Never walk away) - 周杰伦 (Jay Chou)\n[00:03.59]词：方文山\n[00:07.18]曲：周杰伦\n[00:10.77]编曲：林迈可\n[00:14.36]一盏离愁孤灯伫立在窗口\n[00:19.47]\n[00:20.79]我在门后假装你人还没走\n[00:25.72]\n[00:27.30]旧地如重游月圆更寂寞\n[00:32.03]\n[00:33.92]夜半清醒的烛火不忍苛责我\n[00:38.97]\n[00:40.55]一壶漂泊浪迹天涯难入喉\n[00:45.53]\n[00:47.11]你走之后酒暖回忆思念瘦\n[00:52.10]\n[00:53.60]水向东流时间怎么偷\n[00:58.41]\n[01:00.36]花开就一次成熟我却错过\n[01:05.22]\n[01:10.04]谁在用琵琶弹奏一曲东风破\n[01:15.72]\n[01:16.61]岁月在墙上剥落看见小时候\n[01:21.93]\n[01:23.32]犹记得那年我们都还很年幼\n[01:28.49]\n[01:29.69]而如今琴声幽幽我的等候你没听过\n[01:36.33]谁在用琵琶弹奏一曲东风破\n[01:41.69]\n[01:42.83]枫叶将故事染色结局我看透\n[01:48.13]\n[01:49.52]篱笆外的古道我牵着你走过\n[01:54.76]\n[01:56.08]荒烟蔓草的年头就连分手都很沉默\n[02:03.13]\n[02:29.03]一壶漂泊浪迹天涯难入喉\n[02:34.14]\n[02:35.59]你走之后酒暖回忆思念瘦\n[02:40.60]\n[02:42.11]水向东流时间怎么偷\n[02:46.91]\n[02:48.73]花开就一次成熟我却错过\n[02:54.18]\n[02:58.56]谁在用琵琶弹奏一曲东风破\n[03:04.30]\n[03:05.12]岁月在墙上剥落看见小时候\n[03:10.30]\n[03:11.75]犹记得那年我们都还很年幼\n[03:16.86]\n[03:18.31]而如今琴声幽幽我的等候你没听过\n[03:24.88]谁在用琵琶弹奏一曲东风破\n[03:30.24]\n[03:31.57]枫叶将故事染色结局我看透\n[03:36.55]\n[03:38.01]篱笆外的古道我牵着你走过\n[03:43.37]\n[03:44.63]荒烟蔓草的年头就连分手都\n[03:50.24]\n[03:51.19]谁在用琵琶弹奏一曲东风破\n[03:56.74]\n[03:57.63]岁月在墙上剥落看见小时候\n[04:02.87]\n[04:04.25]犹记得那年我们都还很年幼\n[04:09.62]\n[04:10.75]而如今琴声幽幽我的等候你没听过\n[04:17.44]谁在用琵琶弹奏一曲东风破\n[04:22.99]\n[04:24.01]枫叶将故事染色结局我看透\n[04:29.05]\n[04:30.63]篱笆外的古道我牵着你走过\n[04:37.13]荒烟蔓草的年头就连分手都很沉默",
        "url": "http://dl.stream.qqmusic.qq.com/M500003uEbEr0jcW7c.mp3?vkey=AEE74D5DAB8C851E531D4A44DD6AE7CA2047C72D953BFFC60A8CE3D6C858655BFE30013A98BA4F9AA6681B5FDC1C863CFF14847A64503D66&guid=5150825362&fromtag=1",
        "pic": "http://y.gtimg.cn/music/photo_new/T002R300x300M000000MkMni19ClKG.jpg"
    },
    {
        "type": "qq",
        "link": "http://y.qq.com/n/yqq/song/004Yi5BD3ksoAN.html",
        "songid": "004Yi5BD3ksoAN",
        "title": "蒲公英的约定",
        "author": "周杰伦",
        "lrc": "[ti:蒲公英的约定]\n[ar:周杰伦]\n[al:我很忙]\n[by:]\n[offset:0]\n[00:00.00]蒲公英的约定 - 周杰伦 (Jay Chou)\n[00:09.78]词：方文山\n[00:19.57]曲：周杰伦\n[00:29.36]小学篱笆旁的蒲公英\n[00:35.10]\n[00:35.92]是记忆里有味道的风景\n[00:42.07]\n[00:43.04]午睡操场传来蝉的声音\n[00:48.39]\n[00:50.07]多少年后也还是很好听\n[00:56.16]\n[00:57.61]将愿望折纸飞机寄成信\n[01:03.38]\n[01:04.25]因为我们等不到那流星\n[01:10.19]\n[01:11.32]认真投决定命运的硬币\n[01:17.15]\n[01:18.29]却不知道到底能去哪里\n[01:23.88]\n[01:25.61]一起长大的约定\n[01:29.80]\n[01:30.54]那样清晰 拉过勾的我相信\n[01:39.45]说好要一起旅行\n[01:44.68]是你如今 唯一坚持的任性\n[01:54.94]\n[02:22.36]在走廊上罚站打手心\n[02:27.76]\n[02:28.94]我们却注意窗边的蜻蜓\n[02:34.71]\n[02:36.04]我去到哪里你都跟很紧\n[02:41.79]\n[02:43.13]很多的梦在等待着进行\n[02:49.46]\n[02:50.13]一起长大的约定\n[02:54.47]\n[02:55.21]那样清晰 拉过勾的我相信\n[03:04.13]说好要一起旅行\n[03:08.45]\n[03:09.31]是你如今 唯一坚持的任性\n[03:18.31]一起长大的约定\n[03:22.24]\n[03:23.40]那样真心\n[03:26.84]与你聊不完的曾经\n[03:32.39]而我已经分不清\n[03:36.79]\n[03:37.58]你是友情还是错过的爱情",
        "url": "http://dl.stream.qqmusic.qq.com/M500004Yi5BD3ksoAN.mp3?vkey=AEE74D5DAB8C851E531D4A44DD6AE7CA2047C72D953BFFC60A8CE3D6C858655BFE30013A98BA4F9AA6681B5FDC1C863CFF14847A64503D66&guid=5150825362&fromtag=1",
        "pic": "http://y.gtimg.cn/music/photo_new/T002R300x300M000002eFUFm2XYZ7z.jpg"
    },
    {
        "type": "qq",
        "link": "http://y.qq.com/n/yqq/song/001Bbywq2gicae.html",
        "songid": "001Bbywq2gicae",
        "title": "搁浅",
        "author": "周杰伦",
        "lrc": "[ti:搁浅]\n[ar:周杰伦]\n[al:七里香]\n[by:]\n[offset:0]\n[00:00.00]搁浅 - 周杰伦 (Jay Chou)\n[00:05.44]词：宋健彰\n[00:10.89]曲：周杰伦\n[00:16.34]久未放晴的天空\n[00:20.13]依旧留着你的笑容\n[00:24.25]哭过却无法掩埋歉疚\n[00:30.95]\n[00:31.92]风筝在阴天搁浅\n[00:35.33]\n[00:35.87]想念还在等待救援\n[00:39.48]\n[00:40.02]我拉着线复习你给的温柔\n[00:46.08]\n[00:46.67]曝晒在一旁的寂寞\n[00:49.99]\n[00:50.72]笑我给不起承诺\n[00:53.98]怎么会怎么会你竟原谅了我\n[01:00.29]\n[01:01.05]我只能永远读着对白\n[01:05.61]读着我给你的伤害\n[01:09.53]我原谅不了我\n[01:12.19]就请你当作我已不在\n[01:16.78]我睁开双眼看着空白\n[01:21.26]忘记你对我的期待\n[01:25.29]读完了依赖\n[01:27.91]我很快就离开\n[01:34.02]\n[01:54.05]久未放晴的天空\n[01:57.94]依旧留着你的笑容\n[02:01.79]\n[02:02.30]哭过却无法掩埋歉疚\n[02:08.58]\n[02:09.64]风筝在阴天搁浅\n[02:12.91]\n[02:13.50]想念还在等待救援\n[02:18.41]我拉着线复习你给的温柔\n[02:23.72]\n[02:24.29]曝晒在一旁的寂寞\n[02:27.55]\n[02:28.52]笑我给不起承诺\n[02:31.80]怎么会怎么会你竟原谅了我\n[02:38.17]\n[02:39.01]我只能永远读着对白\n[02:43.32]读着我给你的伤害\n[02:47.30]我原谅不了我\n[02:50.06]就请你当作我已不在\n[02:54.58]我睁开双眼看着空白\n[02:58.95]忘记你对我的期待\n[03:02.98]读完了依赖\n[03:05.06]\n[03:05.78]我很快就\n[03:07.91]\n[03:08.98]我只能永远读着对白\n[03:14.63]读着我给你的伤害\n[03:18.53]我原谅不了我\n[03:21.27]就请你当作我已不在\n[03:25.24]\n[03:26.10]我睁开双眼看着空白\n[03:30.20]忘记你对我的期待\n[03:34.18]读完了依赖\n[03:36.39]\n[03:37.05]我很快就离开",
        "url": "http://dl.stream.qqmusic.qq.com/M500001Bbywq2gicae.mp3?vkey=AEE74D5DAB8C851E531D4A44DD6AE7CA2047C72D953BFFC60A8CE3D6C858655BFE30013A98BA4F9AA6681B5FDC1C863CFF14847A64503D66&guid=5150825362&fromtag=1",
        "pic": "http://y.gtimg.cn/music/photo_new/T002R300x300M000003DFRzD192KKD.jpg"
    },
    {
        "type": "qq",
        "link": "http://y.qq.com/n/yqq/song/001xd0HI0X9GNq.html",
        "songid": "001xd0HI0X9GNq",
        "title": "一路向北",
        "author": "周杰伦",
        "lrc": "[ti:一路向北 (电影《头文字D》 插曲)]\n[ar:周杰伦]\n[al:十一月的萧邦]\n[by:]\n[offset:0]\n[00:00.00]一路向北 (《头文字D》电影插曲) - 周杰伦 (Jay Chou)\n[00:12.42]词：方文山\n[00:24.84]曲：周杰伦\n[00:37.27]后视镜里的世界\n[00:41.12]\n[00:44.42]越来越远的道别\n[00:47.98]\n[00:48.90]你转身向背 侧脸还是很美\n[00:54.92]\n[00:55.44]我用眼光去追 竟听见你的泪\n[01:02.39]\n[01:05.89]在车窗外面徘徊 是我错失的机会\n[01:16.93]\n[01:17.49]你站的方位 跟我中间隔着泪\n[01:23.64]街景一直在后退\n[01:26.81]\n[01:27.39]你的崩溃在窗外零碎\n[01:31.60]我一路向北 离开有你的季节\n[01:37.72]\n[01:38.85]你说你好累 已无法再爱上谁\n[01:45.96]风在山路吹\n[01:48.73]过往的画面全都是我不对\n[01:53.36]\n[01:54.08]细数惭愧 我伤你几回\n[01:58.62]\n[02:21.17]后视镜里的世界 越来越远的道别\n[02:31.33]\n[02:32.88]你转身向背 侧脸还是很美\n[02:39.29]我用眼光去追 竟听见你的泪\n[02:45.82]\n[02:49.72]在车窗外面徘徊 是我错失的机会\n[03:00.59]\n[03:01.56]你站的方位 跟我中间隔着泪\n[03:07.46]街景一直在后退\n[03:10.54]\n[03:11.15]你的崩溃在窗外零碎\n[03:15.01]\n[03:15.53]我一路向北 离开有你的季节\n[03:21.64]\n[03:22.90]你说你好累 已无法再爱上谁\n[03:29.94]风在山路吹\n[03:32.62]过往的画面全都是我不对\n[03:37.39]\n[03:37.95]细数惭愧 我伤你几回\n[03:43.66]\n[03:44.23]我一路向北 离开有你的季节\n[03:50.21]\n[03:51.50]方向盘周围 回转着我的后悔\n[03:58.99]我加速超越\n[04:01.37]却甩不掉紧紧跟随的伤悲\n[04:05.87]\n[04:06.75]细数惭愧我 伤你几回\n[04:11.37]\n[04:13.82]停止狼狈就 让错纯粹",
        "url": "http://dl.stream.qqmusic.qq.com/M500001xd0HI0X9GNq.mp3?vkey=AEE74D5DAB8C851E531D4A44DD6AE7CA2047C72D953BFFC60A8CE3D6C858655BFE30013A98BA4F9AA6681B5FDC1C863CFF14847A64503D66&guid=5150825362&fromtag=1",
        "pic": "http://y.gtimg.cn/music/photo_new/T002R300x300M000002MAeob3zLXwZ.jpg"
    },
    {
        "type": "qq",
        "link": "http://y.qq.com/n/yqq/song/004RUiXu49ufy1.html",
        "songid": "004RUiXu49ufy1",
        "title": "菊花台",
        "author": "周杰伦",
        "lrc": "[ti:菊花台]\n[ar:周杰伦]\n[al:依然范特西]\n[by:]\n[offset:0]\n[00:00.00]菊花台 (Chrysanthemum Terrace) (《满城尽带黄金甲》电影片尾曲) - 周杰伦 (Jay Chou)\n[00:12.13]词：方文山\n[00:24.26]曲：周杰伦\n[00:36.40]你的泪光柔弱中带伤\n[00:42.39]\n[00:43.20]惨白的月弯弯勾住过往\n[00:49.34]\n[00:50.15]夜太漫长凝结成了霜\n[00:56.23]\n[00:56.99]是谁在阁楼上冰冷的绝望\n[01:03.58]\n[01:04.11]雨轻轻弹朱红色的窗\n[01:10.60]\n[01:11.11]我一生在纸上被风吹乱\n[01:17.51]\n[01:18.08]梦在远方化成一缕香\n[01:24.29]\n[01:24.94]随风飘散你的模样\n[01:30.25]\n[01:34.80]菊花残满地伤\n[01:38.07]你的笑容已泛黄\n[01:42.41]花落人断肠\n[01:45.01]我心事静静躺\n[01:48.56]北风乱夜未央\n[01:52.00]你的影子剪不断\n[01:56.32]徒留我孤单在湖面成双\n[02:05.47]\n[02:31.38]花已向晚飘落了灿烂\n[02:37.44]\n[02:38.20]凋谢的世道上命运不堪\n[02:45.13]愁莫渡江秋心拆两半\n[02:51.91]怕你上不了岸一辈子摇晃\n[02:58.63]\n[02:59.18]谁的江山马蹄声狂乱\n[03:06.16]我一身的戎装呼啸沧桑\n[03:13.03]天微微亮你轻声的叹\n[03:19.34]\n[03:20.56]一夜惆怅如此委婉\n[03:25.51]\n[03:29.76]菊花残满地伤\n[03:33.05]你的笑容已泛黄\n[03:37.43]花落人断肠\n[03:40.01]我心事静静躺\n[03:43.56]北风乱夜未央\n[03:46.98]你的影子剪不断\n[03:51.30]徒留我孤单在湖面成双\n[04:00.07]\n[04:01.05]菊花残满地伤\n[04:04.38]你的笑容已泛黄\n[04:08.75]花落人断肠\n[04:11.29]我心事静静躺\n[04:14.89]北风乱夜未央\n[04:18.26]你的影子剪不断\n[04:23.75]\n[04:24.49]徒留我孤单在湖面成双",
        "url": "http://dl.stream.qqmusic.qq.com/M500004RUiXu49ufy1.mp3?vkey=AEE74D5DAB8C851E531D4A44DD6AE7CA2047C72D953BFFC60A8CE3D6C858655BFE30013A98BA4F9AA6681B5FDC1C863CFF14847A64503D66&guid=5150825362&fromtag=1",
        "pic": "http://y.gtimg.cn/music/photo_new/T002R300x300M000002jLGWe16Tf1H.jpg"
    },
    {
        "type": "qq",
        "link": "http://y.qq.com/n/yqq/song/0020qX4u2JJRxK.html",
        "songid": "0020qX4u2JJRxK",
        "title": "开不了口",
        "author": "周杰伦",
        "lrc": "[ti:开不了口]\n[ar:周杰伦]\n[al:范特西]\n[by:]\n[offset:0]\n[00:00.00]开不了口 - 周杰伦 (Jay Chou)\n[00:09.34]词：徐若瑄\n[00:18.69]曲：周杰伦\n[00:28.04]才离开没多久就开始\n[00:31.29]担心今天的你过得好不好\n[00:34.72]整个画面是你 想你想的睡不着\n[00:40.09]\n[00:41.71]嘴嘟嘟那可爱的模样\n[00:44.95]还有在你身上香香的味道\n[00:48.45]我的快乐是你 想你想的都会笑\n[00:54.25]\n[00:54.94]没有你在我有多难熬\n[00:58.68]没有你在我有多难熬多烦恼\n[01:01.87]没有你烦我有多烦恼\n[01:05.43]没有你烦我有多烦恼多难熬\n[01:08.79]穿过云层 我试着努力向你奔跑\n[01:14.41]\n[01:15.09]爱才送到 你却已在别人怀抱\n[01:20.71]\n[01:22.02]就是开不了口 让她知道\n[01:26.70]\n[01:27.57]我一定会呵护着你 也逗你笑\n[01:33.32]\n[01:34.87]你对我有多重要\n[01:37.87]我后悔没 让你知道\n[01:41.80]安静的听你撒娇\n[01:44.80]看你睡着 一直到老\n[01:48.23]\n[01:48.98]就是开不了口 让她知道\n[01:54.22]\n[01:54.97]就是那么简单几句 我办不到\n[02:00.90]\n[02:02.27]整颗心悬在半空\n[02:05.26]我只能够 远远看着\n[02:09.13]这些我都做得到\n[02:12.07]\n[02:12.62]但那个人已经不是我\n[02:16.92]\n[02:44.98]没有你在我有多难熬\n[02:48.41]没有你在我有多难熬多烦恼\n[02:51.72]没有你烦我有多烦恼\n[02:55.22]没有你烦我有多烦恼多难熬\n[02:58.52]穿过云层 我试着努力向你奔跑\n[03:04.27]\n[03:04.83]爱才送到 你却已在别人怀抱\n[03:10.50]\n[03:11.75]就是开不了口 让她知道\n[03:16.36]\n[03:17.18]我一定会呵护着你 也逗你笑\n[03:23.04]\n[03:24.54]你对我有多重要\n[03:27.54]我后悔没 让你知道\n[03:31.47]安静的听你撒娇\n[03:34.40]看你睡着 一直到老\n[03:38.08]\n[03:38.77]就是开不了口 让她知道\n[03:43.64]\n[03:44.64]就是那么简单几句 我办不到\n[03:50.56]\n[03:51.94]整颗心悬在半空\n[03:54.93]我只能够 远远看着\n[03:58.87]这些我都做得到\n[04:01.86]但那个人已经不是我",
        "url": "http://dl.stream.qqmusic.qq.com/M5000020qX4u2JJRxK.mp3?vkey=AEE74D5DAB8C851E531D4A44DD6AE7CA2047C72D953BFFC60A8CE3D6C858655BFE30013A98BA4F9AA6681B5FDC1C863CFF14847A64503D66&guid=5150825362&fromtag=1",
        "pic": "http://y.gtimg.cn/music/photo_new/T002R300x300M000000I5jJB3blWeN.jpg"
    },
    {
        "type": "qq",
        "link": "http://y.qq.com/n/yqq/song/00265Jxe3JzXOJ.html",
        "songid": "00265Jxe3JzXOJ",
        "title": "说了再见",
        "author": "周杰伦",
        "lrc": "[ti:说了再见 (《海洋天堂》电影主题曲)]\n[ar:周杰伦]\n[al:跨时代]\n[by:]\n[offset:0]\n[00:00.00]说了再见 (《海洋天堂》电影主题曲) - 周杰伦 (Jay Chou)\n[00:08.09]词：古小力/黄凌嘉\n[00:16.18]曲：周杰伦\n[00:24.27]编曲：钟兴民\n[00:32.37]天凉了 雨下了 你走了\n[00:35.45]\n[00:36.05]清楚了 我爱的 遗失了\n[00:39.24]\n[00:40.14]落叶飘在湖面上睡着了\n[00:45.14]\n[00:47.77]想要放 放不掉 泪在飘\n[00:51.44]你看看 你看看不到\n[00:54.86]我假装过去不重要\n[00:58.62]却发现自己办不到\n[01:02.31]说了再见 才发现再也见不到\n[01:08.09]\n[01:09.92]我不能就这样失去你的微笑\n[01:16.86]\n[01:17.83]口红待在桌角 而你我找不到\n[01:25.87]\n[01:26.73]若角色对调你说好不好\n[01:33.13]说了再见 才发现再也见不到\n[01:40.14]\n[01:40.92]能不能就这样忍着痛泪不掉\n[01:48.62]说好陪我到老 永恒往哪里找\n[01:56.89]\n[01:57.67]再次拥抱一分一秒都好\n[02:04.12]\n[02:20.85]天凉了 雨下了 你走了\n[02:23.69]\n[02:24.34]清楚了 我爱的 遗失了\n[02:27.58]\n[02:28.32]落叶飘在湖面上睡着了\n[02:33.98]\n[02:36.14]想要放 放不掉 泪在飘\n[02:39.80]你看看 你看看不到\n[02:43.24]我假装过去不重要\n[02:47.03]却发现自己办不到\n[02:50.62]说了再见 才发现再也见不到\n[02:58.15]我不能就这样失去你的微笑\n[03:05.91]口红待在桌角 而你我找不到\n[03:14.16]\n[03:14.98]若角色对调你说好不好\n[03:21.59]\n[03:24.08]你的笑 你的好\n[03:26.99]\n[03:27.72]脑海里 一直在绕\n[03:30.89]\n[03:31.54]我的手 忘不了 你手的温度\n[03:38.03]\n[03:38.57]心碎了一地 捡不回\n[03:42.22]从前的心跳 身陷过去我无力逃跑\n[03:52.33]\n[03:52.98]说再见 才发现再也见不到\n[03:59.64]\n[04:00.19]能不能就这样忍着痛泪不掉\n[04:07.91]说好陪我到老 永恒往哪里找\n[04:16.30]\n[04:16.95]再次拥抱一分一秒都好",
        "url": "http://dl.stream.qqmusic.qq.com/M50000265Jxe3JzXOJ.mp3?vkey=AEE74D5DAB8C851E531D4A44DD6AE7CA2047C72D953BFFC60A8CE3D6C858655BFE30013A98BA4F9AA6681B5FDC1C863CFF14847A64503D66&guid=5150825362&fromtag=1",
        "pic": "http://y.gtimg.cn/music/photo_new/T002R300x300M000000bviBl4FjTpO.jpg"
    }
]